Workbook

Sheet README
A1: Project MarginSpring — D2 Data Ingestion & Governance Dataset
A2: Version v1.3 · built 2026-10-23 · Team J (owner: James Mathew) · ANCP Module 2
A4: What this workbook is
A5: The cleaned, versioned dataset for D2. Raw files are never edited; every number here traces to a Source_Log id.
A7: Sheets
A8: Source_Log — every source: publisher, URL, period, date accessed, licence/terms, verification note
A9: Harmonisation — canonical variable definitions and how each firm / Bloomberg labels them
A10: Quarterly_Panel — one row per firm-quarter: Wipro Q1 FY15–Q2 FY27 (50), Infosys Q4 FY19–Q1 FY27, TCS Q4 FY22–Q2 FY27, HCLTech Q2 FY25–Q2 FY27, LTIMindtree Q2 FY23–Q1 FY27, Tech Mahindra Q4 FY24–Q2 FY27. Columns Q–S are D4 controls: wage-hike quarter flag, USD/INR quarterly average, one-off flag
A11: Wage_Hikes — salary-hike effective dates and first fiscal quarter of impact (Wipro FY21–FY27, Infosys FY21–FY27, TCS FY25–FY27)
A12: FX_USDINR — monthly USD/INR (US Federal Reserve G.5 via FRED), Jan 2014–Sep 2026, mapped to fiscal quarters
A13: TCS_Commentary — what TCS management said about utilisation, bench and capacity each quarter around the June 2025 policy
A14: Margin_Walks — management statements of margin change by driver, tiered A/B/C
... A31: Peer data now comes from company filings (v1.1). If refreshed Bloomberg files arrive later, save them to raw/bloomberg_v1, rerun, and use them as a third source; bump the version and log it in Changelog.

Sheet Source_Log
A1: source_id | B1: publisher | C1: document | D1: url | E1: periods_covered | F1: source_type | G1: licence_terms | H1: used_for | I1: verification_note | J1: date_accessed
A2: S01 | B2: Bloomberg L.P. (via XIME terminal) | C2: 26 Excel exports: FA pages (BDH) for WPRO IN; KPI Comparison 'IT Services' (BQL); Company Financial multi-period (BQL) | D2: Bloomberg Terminal (no URL) | E2: FY2015–FY2028E annual; CY2025Q2–CY2027Q1 quarterly | F2: Licensed database | G2: Bloomberg subscription terms: internal academic use; raw data not to be republished | H2: Financial panel (annual), peer KPI panel (once refreshed) | I2: 97.7% of requested cells unevaluated; see Bloomberg_File_Audit | J2: 2026-10-23
A3: S02 | B3: Wipro Ltd | C3: Analyst datasheet Q2 FY27 | D3: https://www.wipro.com/content/dam/nexus/en/investor/quarterly-results/2026-2027/q2fy27/datasheet-q2fy27.pdf | E3: Q1 FY26–Q2 FY27 | F3: Company disclosure (primary) | G3: Public investor disclosure; academic use | H3: Wipro capacity & margin panel | I3: Matches D1 table for all 5 overlapping quarters | J3: 2026-10-23
A4: S03 | B4: Wipro Ltd | C4: Analyst datasheet Q4 FY25 | D4: https://www.wipro.com/content/dam/nexus/en/investor/quarterly-results/2024-2025/q4fy25/datasheet-q4fy25.pdf | E4: Q4 FY24–Q4 FY25 | F4: Company disclosure (primary) | G4: Public investor disclosure; academic use | H4: Wipro panel | J4: 2026-10-23
A5: S04 | B5: Wipro Ltd | C5: Analyst datasheet Q3 FY24 | D5: https://www.wipro.com/content/dam/nexus/en/investor/quarterly-results/2023-2024/q3fy24/datasheet-q3fy24.pdf | E5: Q2–Q3 FY24 | F5: Company disclosure (primary) | G5: Public investor disclosure; academic use | H5: Wipro panel (fills Q3 FY24); cross-checks Q2 FY24 vs S05 | I5: Q2 FY24 identical to S05 | J5: 2026-10-23
A6: S05 | B6: Wipro Ltd | C6: Analyst datasheet Q2 FY24 | D6: https://www.wipro.com/content/dam/nexus/en/investor/quarterly-results/2023-2024/q2fy24/datasheet-q2fy24.pdf | E6: Q1 FY23–Q2 FY24 | F6: Company disclosure (primary) | G6: Public investor disclosure; academic use | H6: Wipro panel | J6: 2026-10-23
A7: S06 | B7: Wipro Ltd | C7: Analyst datasheet Q4 FY22 | D7: https://www.wipro.com/content/dam/nexus/en/investor/quarterly-results/2021-2022/q4fy22/analyst-data-sheet-q4-fy22.pdf | E7: Q4 FY21–Q4 FY22 | F7: Company disclosure (primary) | G7: Public investor disclosure; academic use | H7: Wipro panel (incl. gross utilisation) | J7: 2026-10-23
A8: S07 | B8: Wipro Ltd | C8: Analyst datasheet Q3 FY21 | D8: https://www.wipro.com/content/dam/nexus/en/investor/quarterly-results/2020-2021/q3fy21/analyst-data-sheet-q3-fy21..pdf | E8: Q3 FY21 | F8: Company disclosure (primary) | G8: Public investor disclosure; academic use | H8: Wipro panel (fills Q3 FY21) | J8: 2026-10-23
A9: S08 | B9: Wipro Ltd | C9: Analyst datasheet Q2 FY21 | D9: https://www.wipro.com/content/dam/nexus/en/investor/quarterly-results/2020-2021/q2fy21/analyst-data-sheet-q2-fy21.pdf | E9: Q1 FY20–Q2 FY21 | F9: Company disclosure (primary) | G9: Public investor disclosure; academic use | H9: Wipro panel | J9: 2026-10-23
A10: S09 | B10: Wipro Ltd | C10: Investor quarterly-results index (links to all datasheets FY12–FY27) | D10: https://www.wipro.com/investors/quarterly-results/ | E10: FY12–FY27 | F10: Company website | G10: Public | H10: Locating datasheets for back-fill to 40 quarters | J10: 2026-10-23
A11: S10 | B11: Tata Consultancy Services | C11: Fact sheet Q2 FY27 | D11: https://www.tcs.com/content/dam/tcs/investor-relations/financial-statements/2026-27/q2/Presentations/Q2%202026-27%20Fact%20Sheet.pdf | E11: Q1 FY26–Q2 FY27 | F11: Company disclosure (primary) | G11: Public investor disclosure; academic use | H11: TCS margin & headcount panel | I11: Utilisation not disclosed | J11: 2026-10-23
A12: S11 | B12: HCL Technologies | C12: Investor release Q2 FY27 | D12: https://www.hcltech.com/sites/default/files/document/open/quarter-results/2026-10/hcltech-Q2-fy27-Investor-release.pdf | E12: Q2 FY26–Q2 FY27 | F12: Company disclosure (primary) | G12: Public investor disclosure; academic use | H12: HCLTech margin, headcount, attrition | I12: Utilisation not disclosed | J12: 2026-10-23
A13: S12 | B13: Infosys Ltd | C13: Fact sheet Q1 FY27 | D13: https://www.infosys.com/investors/reports-filings/quarterly-results/2026-2027/q1/documents/fact-sheet.pdf | E13: Q1 FY26, Q4 FY26, Q1 FY27 | F13: Company disclosure (primary) | G13: Public investor disclosure; academic use | H13: Infosys panel | I13: Q4 FY26 margin 20.9 (USD table) vs 21.0 (INR table) | J13: 2026-10-23
A14: S13 | B14: Infosys Ltd | C14: Fact sheet Q2 FY26 | D14: https://www.infosys.com/investors/reports-filings/quarterly-results/2025-2026/q2/documents/fact-sheet.pdf | E14: Q2 FY25, Q1 FY26, Q2 FY26 | F14: Company disclosure (primary) | G14: Public investor disclosure; academic use | H14: Infosys panel | I14: Q1 FY26 identical to S12 | J14: 2026-10-23
A15: S14 | B15: Infosys Ltd via The Motley Fool | C15: Q1 FY27 earnings call transcript (23 Jul 2026) | D15: https://www.fool.com/earnings/call-transcripts/2026/07/23/infosys-infy-q1-2027-earnings-call-transcript/ | E15: Q1 FY27 | F15: Transcript (third-party) | G15: Quoted sparingly; academic use | H15: Margin walk | I15: Utilisation +1.9 pts confirmed vs S12 (83.0→84.9) | J15: 2026-10-23
A16: S15 | B16: Infosys Ltd | C16: Q4 FY25 earnings call transcript | D16: https://www.infosys.com/investors/reports-filings/quarterly-results/2024-2025/q4/documents/transcripts/earningscall.pdf | E16: Q4 FY25 | F16: Transcript (company) | G16: Quoted sparingly; academic use | H16: Margin walk | J16: 2026-10-23
A17: S16 | B17: Infosys Ltd | C17: Q1 FY23 earnings call transcript (24 Jul 2022); also SEC Form 6-K exv99w05 | D17: https://www.infosys.com/investors/reports-filings/quarterly-results/2022-2023/q1/documents/transcripts/earningscall.pdf | E17: Q1 FY23 | F17: Transcript (company) | G17: Quoted sparingly; academic use | H17: Margin walk (Tier A) | I17: Two copies agree (infosys.com and SEC 6-K https://sec.gov/Archives/edgar/data/1067491/000106749122000036/exv99w05.htm) | J17: 2026-10-23
A18: S17 | B18: Infosys Ltd | C18: Q3 FY21 earnings call transcript | D18: https://www.infosys.com/investors/reports-filings/quarterly-results/2020-2021/q3/documents/transcripts/earningscall.pdf | E18: Q3 FY21 | F18: Transcript (company) | G18: Quoted sparingly; academic use | H18: Margin walk (Tier B) | J18: 2026-10-23
A19: S18 | B19: Infosys Ltd | C19: Q3 FY25 earnings call transcript | D19: https://www.infosys.com/investors/reports-filings/quarterly-results/2024-2025/q3/documents/transcripts/earningscall.pdf | E19: Q3 FY25 | F19: Transcript (company) | G19: Quoted sparingly; academic use | H19: Margin walk (Tier C) | J19: 2026-10-23
A20: S19 | B20: Infosys Ltd | C20: Q2 FY25 earnings call transcript | D20: https://www.infosys.com/investors/reports-filings/quarterly-results/2024-2025/q2/documents/transcripts/earningscall.pdf | E20: Q2 FY25 | F20: Transcript (company) | G20: Quoted sparingly; academic use | H20: Margin walk (Tier C) | I20: Utilisation 85.9% matches S13 | J20: 2026-10-23
A21: S20 | B21: Infosys Ltd (SEC Form 6-K) | C21: Q1 FY26 earnings call transcript (23 Jul 2025) | D21: https://www.sec.gov/Archives/edgar/data/1067491/000106749125000022/exv99w05.htm | E21: Q1 FY26 | F21: Regulatory filing | G21: Public filing; academic use | H21: Margin walk (Tier C) | I21: Utilisation 85.2% matches S12/S13 | J21: 2026-10-23
A22: S21 | B22: Infosys Ltd | C22: Q3 FY23 earnings call transcript | D22: https://www.infosys.com/investors/reports-filings/quarterly-results/2022-2023/q3/documents/transcripts/earningscall.pdf | E22: Q3 FY23 | F22: Transcript (company) | G22: Quoted sparingly; academic use | H22: Margin walk (Tier B) | J22: 2026-10-23
A23: S22 | B23: Infosys Ltd (SEC Form 6-K) | C23: Q2 FY24 media call transcript (12 Oct 2023) | D23: https://www.sec.gov/Archives/edgar/data/1067491/000106749123000057/exv99w05.htm | E23: Q2 FY24 | F23: Regulatory filing | G23: Public filing; academic use | H23: Margin walk (Tier B) | J23: 2026-10-23
A24: S23 | B24: Tata Consultancy Services | C24: Q4 FY25 earnings call transcript (10 Apr 2025) | D24: https://www.tcs.com/content/dam/tcs/investor-relations/financial-statements/2024-25/q4/Management Commentary/Transcript of the Q4 2024-25 Earnings Conference Call held at 1900 hrs IST on Apr 10, 2025.pdf | E24: Q4 FY25, FY25 | F24: Transcript (company) | G24: Quoted sparingly; academic use | H24: Margin walk (Tier C) | I24: Named drivers do not sum to reported change | J24: 2026-10-23
A25: S24 | B25: Wipro Ltd via The Motley Fool | C25: Q1 FY21 earnings call transcript (14 Jul 2020) | D25: https://www.fool.com/earnings/call-transcripts/2020/07/14/wipro-limited-wit-q1-2021-earnings-call-transcript.aspx | E25: Q1 FY21 | F25: Transcript (third-party, auto-generated) | G25: Quoted sparingly; academic use | H25: Margin walk (Tier B) | I25: Auto-transcript; components do not reconcile cleanly | J25: 2026-10-23
A26: S25 | B26: Bank of Baroda Capital Markets | C26: HCLTech Q1 FY26 result review (15 Jul 2025) | D26: https://www.barodaetrade.com/Reports/HCLTechnologies-Q1FY26ResultReview15Jul25-Research.pdf | E26: Q1 FY26 | F26: Broker research (secondary) | G26: Publicly posted research; quote only | H26: Margin walk (Tier A) | I26: Agrees with D1 source S33 (80 bps) | J26: 2026-10-23
A27: S26 | B27: Outlook Business | C27: HCLTech shares in focus after Q1 underwhelms (Jul 2025) | D27: https://www.outlookbusiness.com/markets/hcltech-shares-in-focus-after-q1-underwhelms-margin-misses | E27: Q1 FY26 | F27: News (secondary) | G27: Quote only | H27: HCLTech Q1 FY26 margin level | I27: Reports 160 bps fall; Emkay says 170 bps | J27: 2026-10-23
A28: S27 | B28: AlphaStreet | C28: HCLTech Q2 FY24 earnings call insights | D28: https://alphastreet.com/india/hcl-technologies-limited-q2-fy24-earnings-conference-call-insights | E28: Q2 FY24 | F28: Call summary (secondary) | G28: Quote only | H28: Margin walk (Tier B) | J28: 2026-10-23
A29: S28 | B29: Sharekhan | C29: Tech Mahindra Q1 FY26 result note (16 Jul 2025) | D29: https://www.sharekhan.com/MediaGalary/docs/TechM-Jul16_2025-202507171645286735867.pdf | E29: Q1 FY26 | F29: Broker research (secondary) | G29: Publicly posted research; quote only | H29: TechM margin, utilisation (Tier C walk) | I29: Internal conflict: utilisation fall stated as 130 bps and 80 bps | J29: 2026-10-23
A30: S29 | B30: Multibagg | C30: Tech Mahindra Q2 FY27 results | D30: https://www.multibagg.ai/market-pulse/articles/tech-mahindra-q2-fy27-results-cmvaqmppj00052umtdvlhbclv | E30: Q1–Q2 FY27 | F30: News aggregator (secondary) | G30: Quote only | H30: TechM margin, headcount, attrition | I30: Single source; replace with TechM fact sheet | J30: 2026-10-23
A31: S30 | B31: ICICI Direct | C31: LTIMindtree Q2 FY26 result update | D31: https://www.icicidirect.com/mailcontent/idirect_ltim_q2fy26.pdf | E31: Q2 FY25, Q1–Q2 FY26 | F31: Broker research (secondary) | G31: Publicly posted research; quote only | H31: LTIM margin, headcount, attrition | I31: Single source; replace with LTIM fact sheet | J31: 2026-10-23
A32: S31 | B32: PSU Connect | C32: Wipro Q2 FY27: margin improves to 16.5% | D32: https://www.psuconnect.in/financial/wipro-q2-fy27-it-services-flat-qoq-margin-improves-to-16-5 | E32: Q2 FY27 | F32: News (secondary) | G32: Quote only | H32: Second source for Wipro Q2 FY27 margin | I32: Agrees with S02 | J32: 2026-10-23
A33: S32 | B33: Infosys Ltd (SEC Form 6-K) — cited in D1 | C33: Earnings call 2020: 80 bps margin from 2.4% utilisation increase | D33: https://www.sec.gov/Archives/edgar/data/1067491/000106749120000072/exv99w05.htm | E33: 2020 (quarter to confirm) | F33: Regulatory filing | G33: Public filing; academic use | H33: Margin walk (Tier A) | I33: Carried from D1; could not re-open this session (site not reachable) — re-verify quarter | J33: 2026-10-23
A34: S33 | B34: Business Standard — cited in D1 | C34: HCLTech Q1 FY26 results; lower utilisation 80 bps | D34: https://www.business-standard.com/markets/news/hcltech-sees-rating-downgrade-post-q1-results-guidance-disappointment-125071501441_1.html | E34: Q1 FY26 | F34: News (secondary) | G34: Quote only | H34: Second source for HCLTech Q1 FY26 walk | I34: Carried from D1 | J34: 2026-10-23
A35: S34 | B35: Sightsinplus — cited in D1 | C35: Wipro revised bench policy (Oct 2026) | D35: https://www.sightsinplus.com/news/industry-news/wipro-gives-employees-six-months-to-find-new-projects-revised-bench-policy/ | E35: Oct 2026 | F35: News (secondary) | G35: Quote only | H35: Policy event: Wipro 180-day window | I35: Carried from D1; second source pending | J35: 2026-10-23
A36: S35 | B36: Outlook Business — cited in D1 | C36: TCS caps bench time at 35 days | D36: https://www.outlookbusiness.com/corporate/tcs-caps-bench-time-at-35-days-under-new-deployment-policy | E36: Jun 2025 | F36: News (secondary) | G36: Quote only | H36: Policy event: TCS 35-business-day cap | I36: Carried from D1; second source = S40 | J36: 2026-10-23
A37: S36 | B37: Sightsinplus — cited in D1 | C37: TCS builds higher bench despite 2025 policy (Oct 2026) | D37: https://www.sightsinplus.com/news/industry-news/tcs-builds-higher-bench-increases-subcontracting-despite-2025-bench-policy/ | E37: Q2 FY27 | F37: News (secondary) | G37: Quote only | H37: Counter-evidence for TCS before/after | I37: Carried from D1 | J37: 2026-10-23
A38: S37 | B38: Webull — cited in D1 | C38: Wipro Q1 FY27 earnings call transcript (Jul 2026) | D38: https://www.webull.com/news/15239831956513792 | E38: Q1 FY27 | F38: Transcript (third-party) | G38: Quoted sparingly | H38: Target band 17–17.5%; stated drivers | I38: Carried from D1 | J38: 2026-10-23
A39: S38 | B39: Wipro Ltd — cited in D1 | C39: Press release, results for quarter ended 30 Sep 2026 (15 Oct 2026) | D39: https://www.wipro.com/newsroom/press-releases/2026/wipro-announces-results-for-the-quarter-ended-september-30-2026/ | E39: Q2 FY27 | F39: Company disclosure (primary) | G39: Public | H39: Second source for Wipro Q2 FY27 margin | I39: Agrees with S02 | J39: 2026-10-23
A40: S39 | B40: Storyboard18 — cited in D1 | C40: NITES complaint on TCS bench policy (Jul 2025) | D40: https://www.storyboard18.com/how-it-works/tcs-under-fire-for-new-bench-policy-nites-alleges-forced-exits-salary-refund-demands-75206.htm | E40: Jul 2025 | F40: News (secondary) | G40: Quote only | H40: Stakeholder / labour-relations context | I40: Carried from D1 | J40: 2026-10-23
... A42: S41 | B42: Wipro Ltd (Form 20-F FY2026) — cited in D1 | C42: Annual report on Form 20-F | D42: https://www.sec.gov/Archives/edgar/data/0001123799/000119312526253514/wit -20260331.htm | E42: FY2026 | F42: Regulatory filing | G42: Public filing | H42: Cost structure (employee compensation share) | I42: Carried from D1 | J42: 2026-10-23
A43: S42 | B43: Infosys Ltd | C43: Fact sheet Q1 FY23 | D43: https://www.infosys.com/investors/reports-filings/quarterly-results/2022-2023/q1/documents/fact-sheet.pdf | E43: Q1 FY22, Q4 FY22, Q1 FY23 | F43: Company disclosure (primary) | G43: Public investor disclosure; academic use | H43: Infosys panel | J43: 2026-10-23
A44: S43 | B44: Infosys Ltd | C44: Fact sheet Q4 FY23 | D44: https://Www.infosys.com/investors/reports-filings/quarterly-results/2022-2023/q4/documents/fact-sheet.pdf | E44: Q4 FY22, Q3 FY23, Q4 FY23 | F44: Company disclosure (primary) | G44: Public investor disclosure; academic use | H44: Infosys panel | I44: Q4 FY22 identical to S42 | J44: 2026-10-23
A45: S44 | B45: Infosys Ltd | C45: Fact sheet Q2 FY24 | D45: https://Www.infosys.com/investors/reports-filings/quarterly-results/2023-2024/q2/documents/fact-sheet.pdf | E45: Q2 FY23, Q1 FY24, Q2 FY24 | F45: Company disclosure (primary) | G45: Public investor disclosure; academic use | H45: Infosys panel | I45: Q1–Q2 FY24 utilisation matches CFO statement (S22) | J45: 2026-10-23
A46: S45 | B46: Infosys Ltd (infosys.com and SEC Form 6-K Ex. 99.4) | C46: Fact sheet Q1 FY25 | D46: https://infosys.com/investors/reports-filings/quarterly-results/2024-2025/q1/documents/fact-sheet.pdf ; https://www.sec.gov/Archives/edgar/data/1067491/000106749124000026/exv99w04.htm | E46: Q1 FY24, Q4 FY24, Q1 FY25 | F46: Company disclosure + regulatory filing | G46: Public; academic use | H46: Infosys panel | I46: Two copies identical | J46: 2026-10-23
A47: S46 | B47: Infosys Ltd | C47: Fact sheet Q3 FY25 | D47: https://infosys.com/investors/reports-filings/quarterly-results/2024-2025/q3/documents/fact-sheet.pdf | E47: Q3 FY24, Q2 FY25, Q3 FY25 | F47: Company disclosure (primary) | G47: Public investor disclosure; academic use | H47: Infosys panel | J47: 2026-10-23
A48: S47 | B48: Infosys Ltd (SEC Form 6-K Ex. 99.4) | C48: Fact sheet Q4 FY25 | D48: https://www.sec.gov/Archives/edgar/data/1067491/000106749125000010/exv99w04.htm | E48: Q4 FY24, Q3 FY25, Q4 FY25 | F48: Regulatory filing | G48: Public filing; academic use | H48: Infosys panel | I48: Q3 FY25, Q4 FY24 identical to S45/S46 | J48: 2026-10-23
A49: S48 | B49: Infosys Ltd | C49: Fact sheet Q3 FY26 | D49: https://www.infosys.com/investors/reports-filings/quarterly-results/2025-2026/q3/documents/fact-sheet.pdf | E49: Q3 FY25, Q2 FY26, Q3 FY26 | F49: Company disclosure (primary) | G49: Public investor disclosure; academic use | H49: Infosys panel | I49: Q3 FY26 margin 18.4% IFRS; 21.2% excl. Labour Codes | J49: 2026-10-23
A50: S49 | B50: Tata Consultancy Services | C50: Fact sheet Q4 FY23 | D50: https://www.tcs.com/content/dam/tcs/investor-relations/financial-statements/2022-23/q4/Presentations/Q4%20FY%202022-23%20Fact%20sheet.pdf | E50: Q4 FY22–Q4 FY23 | F50: Company disclosure (primary) | G50: Public investor disclosure; academic use | H50: TCS panel | J50: 2026-10-23
A51: S50 | B51: Tata Consultancy Services | C51: Fact sheet Q3 FY24 | D51: https://tcs.com/content/dam/tcs/investor-relations/financial-statements/2023-24/q3/Presentations/Q3 2023-24 Fact Sheet.pdf | E51: Q3 FY23–Q3 FY24 | F51: Company disclosure (primary) | G51: Public investor disclosure; academic use | H51: TCS panel | I51: Q3–Q4 FY23 identical to S49 | J51: 2026-10-23
A52: S51 | B52: Tata Consultancy Services | C52: Fact sheet Q4 FY25 | D52: https://www.tcs.com/content/dam/tcs/investor-relations/financial-statements/2024-25/q4/Presentations/Q4 2024-25 Fact Sheet.pdf | E52: Q4 FY24–Q4 FY25 | F52: Company disclosure (primary) | G52: Public investor disclosure; academic use | H52: TCS panel | J52: 2026-10-23
A53: S52 | B53: HCL Technologies | C53: Investor release Q2 FY26 | D53: https://www.hcltech.com/sites/default/files/document/open/quarter-results/2025-10/HCLTech_Q2_FY26_Investor_Release.pdf | E53: Q2 FY25–Q2 FY26 | F53: Company disclosure (primary) | G53: Public investor disclosure; academic use | H53: HCLTech panel | I53: Two margin charts differ by 0.1 pt for Mar'25 and Sep'25 | J53: 2026-10-23
A54: S53 | B54: HCL Technologies (NSE filing) | C54: Investor release Q4 FY26 (21 Apr 2026) | D54: https://nsearchives.nseindia.com/corporate/HCLTECH_21042026180629_InvestorRelease.pdf | E54: Q4 FY25–Q4 FY26 | F54: Regulatory filing | G54: Public filing; academic use | H54: HCLTech panel; restructuring bps | I54: Gives margins incl. and excl. restructuring | J54: 2026-10-23
A55: S54 | B55: HCL Technologies (NSE filing) | C55: Investor release Q3 FY26 (12 Jan 2026) | D55: https://nsearchives.nseindia.com/corporate/HCLTECH_12012026171644_Investor_Release.pdf | E55: Q3 FY25–Q3 FY26 | F55: Regulatory filing | G55: Public filing; academic use | H55: HCLTech panel | J55: 2026-10-23
A56: S55 | B56: LTIMindtree (BSE filing) | C56: Investor presentation Q3 FY24 (17 Jan 2024) | D56: https://www.bseindia.com/xml-data/corpfiling/AttachHis/579d6bcf-3032-41f4-b989-02c8d31bec47.pdf | E56: Q3 FY23, Q2 FY24, Q3 FY24 | F56: Regulatory filing | G56: Public filing; academic use | H56: LTIM panel | J56: 2026-10-23
A57: S56 | B57: LTIMindtree (BSE filing) | C57: Investor presentation Q4 FY24 (24 Apr 2024) | D57: https://www.bseindia.com/xml-data/corpfiling/AttachHis/1615a09b-d8dd-4802-9864-6d66aa0a9d99.pdf | E57: Q4 FY23, Q3 FY24, Q4 FY24 | F57: Regulatory filing | G57: Public filing; academic use | H57: LTIM panel | I57: Q3 FY24 identical to S55 | J57: 2026-10-23
A58: S57 | B58: ICICI Direct | C58: LTIMindtree Q1 FY26 result update | D58: https://www.icicidirect.com/mailcontent/idirect_ltim_q1fy26.pdf | E58: Q1 FY25, Q4 FY25, Q1 FY26 | F58: Broker research (secondary) | G58: Quote only | H58: LTIM margin, attrition | I58: Q1 FY26 14.3% agrees with S30 | J58: 2026-10-23
A59: S58 | B59: Multibagg | C59: LTIMindtree Q4 FY26 margin outlook | D59: https://www.multibagg.ai/market-pulse/articles/ltimindtree-q4fy26-margin-outlook-cmripw9xs39gcnw0j0n75669g | E59: Q4 FY26 | F59: News aggregator (secondary) | G59: Quote only | H59: LTIM margin | I59: Single source | J59: 2026-10-23
A60: S59 | B60: Tech Mahindra | C60: Fact sheet Q4 FY25 | D60: https://insights.techmahindra.com/investors/tml-q4-fy-25-fact-sheet.pdf | E60: Q4 FY24, Q3 FY25, Q4 FY25 | F60: Company disclosure (primary) | G60: Public investor disclosure; academic use | H60: TechM panel | I60: Utilisation and attrition rounded to whole % | J60: 2026-10-23
A61: S60 | B61: Tech Mahindra (NSE filing) | C61: Investor presentation Q3 FY26 (16 Jan 2026) | D61: https://nsearchives.nseindia.com/corporate/TECHM_16012026161125_SEintimationinvestorPresentationQ3_S.pdf | E61: Q3 FY25–Q3 FY26 | F61: Regulatory filing | G61: Public filing; academic use | H61: TechM panel | I61: Utilisation label not qualified; mapped from chart order | J61: 2026-10-23
A62: S61 | B62: ICICI Direct | C62: Tech Mahindra Q2 FY26 result update | D62: https://www.icicidirect.com/mailcontent/idirect_techm_q2fy26.pdf | E62: Q2 FY25, Q1–Q2 FY26 | F62: Broker research (secondary) | G62: Quote only | H62: TechM margin, headcount | I62: Q1–Q2 FY26 margins and headcount agree with S60 | J62: 2026-10-23
A63: S62 | B63: IIFL (India Infoline) | C63: Tech Mahindra Q1 FY27 results: EBIT margin 14.4% | D63: https://www.indiainfoline.com/news/companies/tech-mahindra-q1-fy27-results-profit-rises-8-2-qoq-to-1465-crore-ebit-margin-expands-to-14-4 | E63: Q1 FY27 | F63: News (secondary) | G63: Quote only | H63: Second source for TechM Q1 FY27 | I63: Agrees with S29 | J63: 2026-10-23
A64: S63 | B64: Tata Consultancy Services | C64: Fact sheet Q1 FY26 | D64: https://www.tcs.com/content/dam/tcs/investor-relations/financial-statements/2025-26/q1/Presentations/Q1%202025-26%20Fact%20Sheet.pdf | E64: Q1 FY25–Q1 FY26 | F64: Company disclosure (primary) | G64: Public investor disclosure; academic use | H64: TCS panel | I64: Q1–Q4 FY25 identical to S51 | J64: 2026-10-23
A65: S64 | B65: Tata Consultancy Services | C65: Fact sheet Q1 FY27 | D65: https://www.tcs.com/content/dam/tcs/investor-relations/financial-statements/2026-27/q1/Presentations/Q1%202026-27%20Fact%20Sheet.pdf | E65: Q1 FY26–Q1 FY27 | F65: Company disclosure (primary) | G65: Public investor disclosure; academic use | H65: TCS panel | I65: Q1 FY26–Q1 FY27 identical to S10/S63 | J65: 2026-10-23
A66: S65 | B66: Wipro Ltd | C66: Analyst datasheet Q4 FY15 | D66: https://www.wipro.com/content/dam/nexus/en/investor/quarterly-results/2014-2015/q4/11377-Data-Sheet-Q4-FY15.pdf | E66: Q4 FY14–Q4 FY15 | F66: Company disclosure (primary) | G66: Public investor disclosure; academic use | H66: Wipro panel FY15 | I66: Q4 FY15 identical to S66 | J66: 2026-10-23
A67: S66 | B67: Wipro Ltd | C67: Analyst datasheet Q4 FY16 | D67: https://www.wipro.com/content/dam/nexus/en/investor/quarterly-results/2015-2016/q4/11344-Data-Sheet-Q4-FY16.pdf | E67: Q4 FY15–Q4 FY16 | F67: Company disclosure (primary) | G67: Public investor disclosure; academic use | H67: Wipro panel FY16 | I67: Q4 FY16 later restated in S67 (margin 19.7%, headcount 156,831) | J67: 2026-10-23
A68: S67 | B68: Wipro Ltd | C68: Analyst datasheet Q4 FY17 | D68: https://www.wipro.com/content/dam/nexus/en/investor/quarterly-results/2016-2017/q4/11811-Data-Sheet-Q4-FY-17.pdf | E68: Q4 FY16–Q4 FY17 | F68: Company disclosure (primary) | G68: Public investor disclosure; academic use | H68: Wipro panel FY17 | I68: Q4 FY17 identical to S68 | J68: 2026-10-23
... A74: S73 | B74: Infosys Ltd | C74: Fact sheet Q4 FY20 | D74: https://Www.infosys.com/investors/reports-filings/quarterly-results/2019-2020/q4/documents/fact-sheet.pdf | E74: Q4 FY19, Q3 FY20, Q4 FY20 | F74: Company disclosure (primary) | G74: Public investor disclosure; academic use | H74: Infosys panel | I74: Q4 FY20 identical to S71 | J74: 2026-10-23
A75: S74 | B75: Infosys Ltd | C75: Q1 FY20 earnings call transcript | D75: https://www.infosys.com/investors/reports-filings/quarterly-results/2019-2020/q1/Documents/transcripts/earningscall.pdf | E75: Q1 FY20 | F75: Transcript (company) | G75: Quoted sparingly; academic use | H75: Margin walk (Tier A); Q1 FY20 margin and utilisation | J75: 2026-10-23
A76: S75 | B76: Infosys Ltd | C76: Fact sheet Q3 FY22 | D76: https://www.infosys.com/investors/reports-filings/quarterly-results/2021-2022/q3/documents/fact-sheet.pdf | E76: Q3 FY21, Q2 FY22, Q3 FY22 | F76: Company disclosure (primary) | G76: Public investor disclosure; academic use | H76: Infosys panel | I76: Q3 FY21 utilisation matches S71 and transcript S17 | J76: 2026-10-23
A77: S76 | B77: Infosys Ltd | C77: Q4 FY18 earnings call transcript (infosys.com; also SEC 6-K) | D77: https://www.infosys.com/investors/reports-filings/quarterly-results/2017-2018/q4/documents/transcripts/earningscall.pdf ; https://www.sec.gov/Archives/edgar/data/0001067491/000106749118000014/exv99w06.htm | E77: Q4 FY18 | F77: Transcript (company) | G77: Quoted sparingly; academic use | H77: Margin walk (Tier B) | I77: Two copies agree | J77: 2026-10-23
A78: S77 | B78: Infosys Ltd (SEC Form 6-K) | C78: Q2 FY19 earnings call transcript (16 Oct 2018) | D78: https://www.sec.gov/Archives/edgar/data/0001067491/000106749118000046/exv99w06.htm | E78: Q2 FY19 | F78: Regulatory filing | G78: Public filing | H78: Margin walk (Tier A, year-on-year) | J78: 2026-10-23
A79: S78 | B79: Infosys Ltd (SEC Form 6-K) | C79: Q3 FY19 earnings call transcript (11 Jan 2019) | D79: https://www.sec.gov/Archives/edgar/data/1067491/000106749119000004/exv99w05.htm | E79: Q3 FY19 | F79: Regulatory filing | G79: Public filing | H79: Margin walk (Tier B) | J79: 2026-10-23
A80: S79 | B80: Bullfincher (transcript host) | C80: Infosys Q2 FY20 earnings call | D80: https://bullfincher.io/companies/infosys-limited/earnings-call/fy2020-q2 | E80: Q2 FY20 | F80: Transcript (third-party) | G80: Quoted sparingly | H80: Margin walk (Tier B) | I80: Source shows '110% basis points' (typo for 110 bps) | J80: 2026-10-23
A81: S80 | B81: Tech Mahindra | C81: Q3 FY19 earnings call transcript | D81: https://insights.techmahindra.com/investors/Earnings-Call-Transcript-Q3-FY19.pdf | E81: Q3 FY19 | F81: Transcript (company) | G81: Quoted sparingly; academic use | H81: Margin walk (Tier A) | J81: 2026-10-23
A82: S81 | B82: Tech Mahindra | C82: Q4 FY19 earnings call transcript | D82: https://insights.techmahindra.com/investors/Earnings-Call-Transcript-Q4-FY19.pdf | E82: Q4 FY19 | F82: Transcript (company) | G82: Quoted sparingly | H82: Context: utilisation 'down to 82%' | J82: 2026-10-23
A83: S82 | B83: Tech Mahindra | C83: Q2 FY20 earnings call transcript | D83: https://insights.techmahindra.com/investors/Q2-FY20-call-transcript.pdf | E83: Q2 FY20 | F83: Transcript (company) | G83: Quoted sparingly | H83: Searched; no utilisation bps | J83: 2026-10-23
A84: S83 | B84: Tech Mahindra | C84: Q3 FY16 earnings call transcript | D84: https://insights.techmahindra.com/investors/Earnings-CallTranscripts-Q3FY16.pdf | E84: Q3 FY16 | F84: Transcript (company) | G84: Quoted sparingly | H84: Margin walk (Tier C) | J84: 2026-10-23
A85: S84 | B85: Tata Consultancy Services | C85: Q2 FY26 earnings call transcript (9 Oct 2025) | D85: https://www.tcs.com/content/dam/tcs/investor-relations/financial-statements/2025-26/q2/Management%20Commentary/Transcript%20of%20the%20Q2%202025-26%20Earnings%20Conference%20Call%20held%20at%201900%20hrs%20IST%20on%20October%209,%202025.pdf | E85: Q2 FY26 | F85: Transcript (company, edited) | G85: Quoted sparingly | H85: TCS commentary; margin walk (Tier C); wage-hike timing | J85: 2026-10-23
A86: S85 | B86: Tata Consultancy Services | C86: Q1 FY27 earnings call transcript (9 Jul 2026) | D86: https://www.tcs.com/content/dam/tcs/investor-relations/financial-statements/2026-27/q1/Management%20Commentary/Transcript%20of%20the%20Q1%202026-27%20Earnings%20Conference%20Call%20held%20on%20Jul%209,%202026.pdf | E86: Q1 FY27 | F86: Transcript (company, edited) | G86: Quoted sparingly | H86: TCS commentary; wage impact 170 bps | J86: 2026-10-23
A87: S86 | B87: Tata Consultancy Services (NSE filing) | C87: Q2 FY27 earnings call transcript (8 Oct 2026) | D87: https://nsearchives.nseindia.com/corporate/TCS_CORPCS_14102026155941_SEInt14102026_signed.pdf | E87: Q2 FY27 | F87: Regulatory filing | G87: Public filing | H87: TCS commentary: higher bench, more subcontractors | I87: Primary source for the D1 counter-evidence (S36) | J87: 2026-10-23
A88: S87 | B88: PL Capital (Prabhudas Lilladher) | C88: Tech Mahindra Q1 FY27 update (17 Jul 2026) | D88: https://plindia.com/ResReport/TECHM-17-7-26-PL.pdf | E88: Q1 FY25–Q1 FY27 | F88: Broker research (secondary) | G88: Quote only | H88: TechM margin, utilisation excl. trainees, headcount, attrition | I88: Matches company presentation S60 on every overlapping quarter | J88: 2026-10-23
A89: S88 | B89: Bank of Baroda Capital Markets | C89: LTIMindtree Q2 FY26 result review (17 Oct 2025) | D89: https://www.barodaetrade.com/Reports/LTIMindtree-Q2FY26ResultReview17Oct25-Research.pdf | E89: Q2 FY23–Q2 FY26 | F89: Broker research (secondary) | G89: Quote only | H89: LTIM margin, utilisation, headcount, attrition | I89: Utilisation row labelled 'including trainees' but values equal company 'excl. trainees' figures (S55, S56) and text says excl.; treated as excl. | J89: 2026-10-23
A90: S89 | B90: Sahi (news) | C90: LTIMindtree Q1 FY27 results (13 Jul 2026) | D90: https://www.sahi.com/news/ltimindtree-q1-profit-rises-5-5-to-1-466-crore-as-margins-expand-to-15-5-3147-PE1_COR | E90: Q4 FY26–Q1 FY27 | F90: News (secondary) | G90: Quote only | H90: LTIM margin | I90: Q4 FY26 15.14% conflicts with S58 (15.5%) | J90: 2026-10-23
A91: S90 | B91: CompoundingAI (news) | C91: LTIMindtree Q1 FY27 results analysis | D91: https://compoundingai.in/market-news/ltim-q1-fy27-results-analysis | E91: Q1 FY27 | F91: News (secondary) | G91: Quote only | H91: LTIM margin and attrition | I91: Agrees with S89 | J91: 2026-10-23
A92: S91 | B92: Board of Governors of the Federal Reserve System, via FRED (St. Louis Fed) | C92: Indian Rupees to U.S. Dollar Spot Exchange Rate (EXINUS), monthly, Release G.5 | D92: https://fred.stlouisfed.org/data/EXINUS | E92: Jan 2014–Sep 2026 | F92: Official statistics | G92: Public domain (US government data) | H92: USD/INR control variable | I92: Monthly averages of daily noon buying rates in New York; Sep 2026 preliminary | J92: 2026-10-23
A93: S92 | B93: HR Katha | C93: Wipro to roll out salary hikes in September 2024 (18 Sep 2024) | D93: https://www.hrkatha.com/news/compensation-benefits/wipro-to-roll-out-salary-hikes-in-september-2024/ | E93: FY25 | F93: News (secondary) | G93: Quote only | H93: Wage-hike timing | J93: 2026-10-23
A94: S93 | B94: Trak.in | C94: Wipro salary hike from December 1, 2023 (13 Oct 2023) | D94: https://trak.in/stories/wipro-will-roll-out-salary-hike-for-eligible-employees-from-december-1st-salary-hike-was-due-in-september-2023/ | E94: FY24 | F94: News (secondary) | G94: Quote only | H94: Wage-hike timing | J94: 2026-10-23
A95: S94 | B95: Outlook Business | C95: Wipro: first salary hike in 18 months from March 1 (13 Feb 2026) | D95: https://www.outlookbusiness.com/corporate/wipro-employees-to-get-first-salary-hike-in-18-months-from-march-1 | E95: FY26 | F95: News (secondary) | G95: Quote only | H95: Wage-hike timing; confirms no hike between Sep 2024 and Mar 2026 | J95: 2026-10-23
A96: S95 | B96: People Matters | C96: Wipro postpones salary hikes (Jul 2023), quoting CFO Jatin Dalal | D96: https://www.peoplematters.in/news/compensation-benefits/wipro-postpones-salary-hikes-implements-80-variable-pay-for-q1fy24-38438 | E96: FY23 | F96: News quoting CFO | G96: Quote only | H96: Wage-hike timing: 'last salary increase in September of last year' (Sep 2022) | J96: 2026-10-23
A97: S96 | B97: The News Minute | C97: Wipro announces pay hike for 80% of workforce, second this year (18 Jun 2021) | D97: https://www.thenewsminute.com/atom/wipro-announces-pay-hike-80-workforce-second-hike-year-150913 | E97: FY21–FY22 | F97: News quoting company statement | G97: Quote only | H97: Wage-hike timing: Jan 2021, Jun 2021 (managers+), Sep 2021 | J97: 2026-10-23
A98: S97 | B98: People Matters | C98: TCS rolls out pay hikes for 80% of employees after five-month delay (2 Sep 2025) | D98: https://www.peoplematters.in/news/compensation-benefits/tcs-rolls-out-pay-hikes-for-80percent-of-employees-after-five-month-delay-43253 | E98: FY26 | F98: News (secondary) | G98: Quote only | H98: Wage-hike timing; usual cycle April | I98: CFO confirms on S84 | J98: 2026-10-23
A99: S98 | B99: Angel One | C99: TCS annual salary hike effective April 1, 2026 (10 Apr 2026) | D99: https://oga-prod.angelone.in/news/stocks/tcs-to-roll-out-annual-salary-hike-across-employees-effective-april-1-2026 | E99: FY27 | F99: News (secondary) | G99: Quote only | H99: Wage-hike timing | I99: CFO confirms 170 bps impact on S85 | J99: 2026-10-23
A100: S99 | B100: People Matters | C100: TCS salary hike effective April 1, 2024 (19 Mar 2024) | D100: https://www.peoplematters.in/news/compensation-benefits/tcs-salary-hike-onsite-and-offsite-workers-to-see-large-raise-disparity-40650 | E100: FY25 | F100: News (secondary) | G100: Quote only | H100: Wage-hike timing | J100: 2026-10-23
A101: S100 | B101: People Matters | C101: TCS resumes April salary hikes (9 Apr 2026) | D101: https://www.peoplematters.in/news/compensation-benefits/tcs-resumes-april-salary-hikes-after-delay-with-double-digit-raises-for-top-performers-49180 | E101: FY26–FY27 | F101: News (secondary) | G101: Quote only | H101: Second source for TCS Sep 2025 and Apr 2026 hikes | J101: 2026-10-23
A102: S101 | B102: Business Today | C102: Infosys to roll out salary hikes in three phases from October (23 Jul 2026) | D102: https://www.businesstoday.in/latest/corporate/story/infosys-to-roll-out-salary-hikes-in-three-phases-from-october-senior-employees-to-get-increments-in-january-544896-2026-07-23 | E102: FY27 | F102: News quoting CEO | G102: Quote only | H102: Wage-hike timing (after panel end) | J102: 2026-10-23
A103: S102 | B103: Business Today | C103: Infosys CFO: second pay hike done (23 Jul 2025) | D103: https://www.businesstoday.in/amp/latest/corporate/story/infosys-salary-hike-second-pay-hike-done-but-next-one-says-it-major-cfo-485993-2025-07-23 | E103: FY25–FY26 | F103: News quoting CFO | G103: Quote only | H103: Wage-hike timing: Jan 2025 and 1 Apr 2025 | I103: Consistent with Q1 FY26 walk (S20: compensation −100 bps) | J103: 2026-10-23
A104: S103 | B104: HRD (hcamag.com) | C104: Infosys delaying annual salary hikes to 4th quarter (7 Jan 2025) | D104: https://www.hcamag.com/au/specialisation/benefits/infosys-delaying-annual-salary-hikes-to-4th-quarter-reports/519471 | E104: FY24–FY25 | F104: News (secondary) | G104: Quote only | H104: Wage-hike timing: last hike Nov 2023 | J104: 2026-10-23
A105: S104 | B105: The News Minute | C105: Infosys announces salary hikes effective January 1, 2021 (14 Oct 2020) | D105: https://www.thenewsminute.com/article/infosys-announces-salary-hikes-100-variable-pay-and-special-incentive-employees-135334 | E105: FY21 | F105: News quoting COO | G105: Quote only | H105: Wage-hike timing | J105: 2026-10-23
A106: S105 | B106: Tata Consultancy Services | C106: Q1 FY26 earnings call transcript (10 Jul 2025) | D106: https://www.tcs.com/content/dam/tcs/investor-relations/financial-statements/2025-26/q1/Management%20Commentary/Transcript%20of%20the%20Q1%202025-26%20Earnings%20Conference%20Call%20held%20at%201900%20hrs%20IST%20on%20Jul%2010,%202025.pdf | E106: Q1 FY26 | F106: Transcript (company, edited) | G106: Quoted sparingly | H106: TCS commentary: utilisation fell in the policy quarter | J106: 2026-10-23
...

Sheet Harmonisation
A1: canonical_variable | B1: definition | C1: unit | D1: Wipro label | E1: Infosys label | F1: TCS label | G1: HCLTech label | H1: LTIMindtree label | I1: Tech Mahindra label | J1: Bloomberg mnemonic | K1: harmonisation rule / caveat
A2: op_margin_pct | B2: Operating (EBIT) margin, % of revenue, as reported for the quarter | C2: % | D2: IT Services segment operating margin (datasheet 'Operating Margin %') | E2: Company operating margin (fact sheet) | F2: Company operating margin excl. exceptional items | G2: Company EBIT incl. restructuring; IT&BS segment EBIT in notes | H2: Company EBIT margin | I2: Company EBIT margin | J2: CB_IS_ADJ_OPERATING_MARGIN (adjusted, company level) / CB_IS_OPERATING_MARGIN | K2: Not like-for-like: Wipro is a segment margin. Compare changes (bps QoQ), not levels, across firms. Record basis in margin_basis.
A3: util_excl_trainees_pct | B3: Billable effort / total effort of delivery staff excluding trainees | C3: % | D3: 'Net Utilization (Excluding Trainees)' | E3: 'Utilization – excluding trainees' | F3: Not disclosed | G3: Not disclosed (dropped from releases) | H3: Reported in fact sheet (collect) | I3: Reported incl. trainees in notes; confirm | J3: UTILIZATION_RATE (definition varies by firm — check field notes on terminal) | K3: Primary capacity variable. Do not mix with incl-trainee series.
A4: util_gross_or_incl_trainees_pct | B4: Utilisation including trainees (Infosys) / gross utilisation (Wipro, to FY22) | C4: % | D4: 'Gross Utilization' (FY20–FY22 only) | E4: 'Utilization – including trainees' | F4: Not disclosed | G4: Not disclosed | H4: Check fact sheet | I4: 'Utilisation' (incl. trainees) | J4: — | K4: Secondary series; used only for robustness checks.
A5: headcount | B5: Closing total employees at quarter end | C5: persons | D5: 'Closing Employee Count' | E5: 'Total employees' | F5: 'Total Employee Base' | G5: 'Total headcount' | H5: Total headcount | I5: Total headcount | J5: NUM_OF_EMPLOYEES | K5: Includes BPO/BPS staff where firm does.
A6: vol_attrition_ttm_pct | B6: Voluntary attrition, trailing twelve months, IT services | C6: % | D6: 'Voluntary TTM (IT Services excl. DOP/BPS)' | E6: 'Voluntary attrition % (LTM, IT Services)' | F6: 'Attrition (LTM, IT Services)' | G6: Attrition LTM excl. involuntary & DPO | H6: Attrition LTM | I6: IT attrition LTM | J6: ATTRITION_RATE | K6: Definitions close; minor scope differences noted.
A7: it_rev_usd_mn | B7: IT services revenue in USD million | C7: USD mn | D7: 'IT Services Revenues ($Mn)' | E7: Revenue US$ mn (company) | F7: Revenue US$ mn (company) | G7: Revenue US$ mn | H7: Revenue US$ mn | I7: Revenue US$ mn | J7: SALES_REV_TURN (segment SEG0000403243 for Wipro IT Services) | K7: Wipro only collected in v1.0.
A8: cc_qoq_pct | B8: Sequential revenue growth in constant currency | C8: % | D8: 'Sequential Growth in Constant Currency' | E8: QoQ CC | F8: 'Q-o-Q Growth CC' | G8: QoQ CC | H8: QoQ CC | I8: QoQ CC | J8: Constant Currency Revenue Growth (%) in KPIC | K8: Control variable for D4 regression.
A9: util_bps | B9: Margin change attributed by management to utilisation, bps | C9: bps | D9: Earnings call | E9: Earnings call | F9: Earnings call | G9: Earnings call / broker note | H9: Earnings call | I9: Earnings call | J9: — | K9: Tier A = utilisation isolated; B = bundled with other levers; C = named only.
A10: fiscal_quarter | B10: Indian fiscal quarter label | C10: text | D10: Q1 = Apr–Jun | E10: same | F10: same | G10: same | H10: same | I10: same | J10: FPR 'YYYY Qn' with FYE='C' is calendar: CY2026 Q3 = Q2 FY27 | K10: Mapping implemented in ingest_bloomberg.calendar_to_wipro_fq()

Sheet Quarterly_Panel
A1: firm | B1: fiscal_quarter | C1: quarter_end | D1: op_margin_pct | E1: margin_basis | F1: util_excl_trainees_pct | G1: util_gross_or_incl_trainees_pct | H1: headcount | I1: vol_attrition_ttm_pct | J1: it_rev_usd_mn | K1: cc_qoq_pct | L1: source_id | M1: source_type | N1: note | O1: qoq_margin_bps | P1: qoq_util_pts | Q1: wage_hike_qtr | R1: usd_inr_qavg | S1: one_off_flag
A2: Wipro | B2: Q1 FY15 | C2: 2014-06-30 | D2: 22.8 | E2: IT Services segment operating margin | F2: 77.9 | G2: 68.7 | H2: 147452 | I2: 16.1 | J2: 1740.2 | K2: 0.3 | L2: S65 | M2: Company datasheet | N2: Headcount = IT Services | Q2: =IF(COUNTIFS(Wage_Hikes!$A:$A,A2,Wage_Hikes!$D:$D,B2)>0,1,0) -> 0 | R2: =IFERROR(AVERAGEIFS(FX_USDINR!$B:$B,FX_USDINR!$C:$C,B2),"") -> 59.789133 | S2: 0
A3: Wipro | B3: Q2 FY15 | C3: 2014-09-30 | D3: 22 | E3: IT Services segment operating margin | F3: 79.4 | G3: 70 | H3: 154297 | I3: 16.5 | J3: 1771.5 | K3: 3 | L3: S65 | M3: Company datasheet | N3: Headcount = IT Services | O3: =IF(AND(TRUE(),ISNUMBER(D3),ISNUMBER(D2)),(D3-D2)*100,"") -> -80 | P3: =IF(AND(ISNUMBER(F3),ISNUMBER(F2)),F3-F2,"") -> 1.5 | Q3: =IF(COUNTIFS(Wage_Hikes!$A:$A,A3,Wage_Hikes!$D:$D,B3)>0,1,0) -> 0 | R3: =IFERROR(AVERAGEIFS(FX_USDINR!$B:$B,FX_USDINR!$C:$C,B3),"") -> 60.622333 | S3: 0
A4: Wipro | B4: Q3 FY15 | C4: 2014-12-31 | D4: 21.8 | E4: IT Services segment operating margin | F4: 78.8 | G4: 68.5 | H4: 156866 | I4: 16.5 | J4: 1795.4 | K4: 3.7 | L4: S65 | M4: Company datasheet | N4: Headcount = IT Services | O4: =IF(AND(TRUE(),ISNUMBER(D4),ISNUMBER(D3)),(D4-D3)*100,"") -> -20 | P4: =IF(AND(ISNUMBER(F4),ISNUMBER(F3)),F4-F3,"") -> -0.6 | Q4: =IF(COUNTIFS(Wage_Hikes!$A:$A,A4,Wage_Hikes!$D:$D,B4)>0,1,0) -> 0 | R4: =IFERROR(AVERAGEIFS(FX_USDINR!$B:$B,FX_USDINR!$C:$C,B4),"") -> 61.9189 | S4: 0
A5: Wipro | B5: Q4 FY15 | C5: 2015-03-31 | D5: 22 | E5: IT Services segment operating margin | F5: 80.5 | G5: 70.5 | H5: 158217 | I5: 16.5 | J5: 1774.5 | K5: 1.2 | L5: S65;S66 | M5: Company datasheet | N5: Headcount = IT Services; identical in two sheets | O5: =IF(AND(TRUE(),ISNUMBER(D5),ISNUMBER(D4)),(D5-D4)*100,"") -> 20 | P5: =IF(AND(ISNUMBER(F5),ISNUMBER(F4)),F5-F4,"") -> 1.7 | Q5: =IF(COUNTIFS(Wage_Hikes!$A:$A,A5,Wage_Hikes!$D:$D,B5)>0,1,0) -> 0 | R5: =IFERROR(AVERAGEIFS(FX_USDINR!$B:$B,FX_USDINR!$C:$C,B5),"") -> 62.200333 | S5: 0
A6: Wipro | B6: Q1 FY16 | C6: 2015-06-30 | D6: 21 | E6: IT Services segment operating margin | F6: 81.9 | G6: 71.3 | H6: 161789 | I6: 16.4 | J6: 1794.1 | K6: 0.2 | L6: S66 | M6: Company datasheet | N6: Headcount = IT Services | O6: =IF(AND(TRUE(),ISNUMBER(D6),ISNUMBER(D5)),(D6-D5)*100,"") -> -100 | P6: =IF(AND(ISNUMBER(F6),ISNUMBER(F5)),F6-F5,"") -> 1.4 | Q6: =IF(COUNTIFS(Wage_Hikes!$A:$A,A6,Wage_Hikes!$D:$D,B6)>0,1,0) -> 0 | R6: =IFERROR(AVERAGEIFS(FX_USDINR!$B:$B,FX_USDINR!$C:$C,B6),"") -> 63.3791 | S6: 0
A7: Wipro | B7: Q2 FY16 | C7: 2015-09-30 | D7: 20.7 | E7: IT Services segment operating margin | F7: 82.3 | G7: 69.5 | H7: 168396 | I7: 16.4 | J7: 1831.9 | K7: 3.1 | L7: S66 | M7: Company datasheet | N7: Headcount = IT Services | O7: =IF(AND(TRUE(),ISNUMBER(D7),ISNUMBER(D6)),(D7-D6)*100,"") -> -30 | P7: =IF(AND(ISNUMBER(F7),ISNUMBER(F6)),F7-F6,"") -> 0.4 | Q7: =IF(COUNTIFS(Wage_Hikes!$A:$A,A7,Wage_Hikes!$D:$D,B7)>0,1,0) -> 0 | R7: =IFERROR(AVERAGEIFS(FX_USDINR!$B:$B,FX_USDINR!$C:$C,B7),"") -> 64.9561 | S7: 0
A8: Wipro | B8: Q3 FY16 | C8: 2015-12-31 | D8: 20.2 | E8: IT Services segment operating margin | F8: 78 | G8: 66.4 | H8: 170664 | I8: 16.3 | J8: 1838.3 | K8: 1.4 | L8: S66 | M8: Company datasheet | N8: Headcount = IT Services | O8: =IF(AND(TRUE(),ISNUMBER(D8),ISNUMBER(D7)),(D8-D7)*100,"") -> -50 | P8: =IF(AND(ISNUMBER(F8),ISNUMBER(F7)),F8-F7,"") -> -4.3 | Q8: =IF(COUNTIFS(Wage_Hikes!$A:$A,A8,Wage_Hikes!$D:$D,B8)>0,1,0) -> 0 | R8: =IFERROR(AVERAGEIFS(FX_USDINR!$B:$B,FX_USDINR!$C:$C,B8),"") -> 65.876167 | S8: 0
A9: Wipro | B9: Q4 FY16 | C9: 2016-03-31 | D9: 20.1 | E9: IT Services segment operating margin | F9: 77.5 | G9: 68.1 | H9: 172912 | I9: 16.1 | J9: 1882 | K9: 2.7 | L9: S66 | M9: Company datasheet | N9: As originally reported; restated in S67 to margin 19.7%, headcount 156,831 (definition change) | O9: =IF(AND(TRUE(),ISNUMBER(D9),ISNUMBER(D8)),(D9-D8)*100,"") -> -10 | P9: =IF(AND(ISNUMBER(F9),ISNUMBER(F8)),F9-F8,"") -> -0.5 | Q9: =IF(COUNTIFS(Wage_Hikes!$A:$A,A9,Wage_Hikes!$D:$D,B9)>0,1,0) -> 0 | R9: =IFERROR(AVERAGEIFS(FX_USDINR!$B:$B,FX_USDINR!$C:$C,B9),"") -> 67.487867 | S9: 0
A10: Wipro | B10: Q1 FY17 | C10: 2016-06-30 | D10: 17.8 | E10: IT Services segment operating margin | F10: 79.7 | G10: 69.9 | H10: 158272 | I10: 16.5 | J10: 1930.8 | K10: 2 | L10: S67 | M10: Company datasheet | N10: Headcount basis restated from FY17 (break vs FY16) | O10: =IF(AND(TRUE(),ISNUMBER(D10),ISNUMBER(D9)),(D10-D9)*100,"") -> -230 | P10: =IF(AND(ISNUMBER(F10),ISNUMBER(F9)),F10-F9,"") -> 2.2 | Q10: =IF(COUNTIFS(Wage_Hikes!$A:$A,A10,Wage_Hikes!$D:$D,B10)>0,1,0) -> 0 | R10: =IFERROR(AVERAGEIFS(FX_USDINR!$B:$B,FX_USDINR!$C:$C,B10),"") -> 66.858967 | S10: 0
A11: Wipro | B11: Q2 FY17 | C11: 2016-09-30 | D11: 17.8 | E11: IT Services segment operating margin | F11: 82.8 | G11: 71.2 | H11: 159791 | I11: 16.6 | J11: 1916.3 | K11: 0.9 | L11: S67 | M11: Company datasheet | O11: =IF(AND(TRUE(),ISNUMBER(D11),ISNUMBER(D10)),(D11-D10)*100,"") -> 0 | P11: =IF(AND(ISNUMBER(F11),ISNUMBER(F10)),F11-F10,"") -> 3.1 | Q11: =IF(COUNTIFS(Wage_Hikes!$A:$A,A11,Wage_Hikes!$D:$D,B11)>0,1,0) -> 0 | R11: =IFERROR(AVERAGEIFS(FX_USDINR!$B:$B,FX_USDINR!$C:$C,B11),"") -> 66.9251 | S11: 0
A12: Wipro | B12: Q3 FY17 | C12: 2016-12-31 | D12: 18.3 | E12: IT Services segment operating margin | F12: 81.9 | G12: 71.6 | H12: 164176 | I12: 16.3 | J12: 1902.8 | K12: 0.6 | L12: S67 | M12: Company datasheet | O12: =IF(AND(TRUE(),ISNUMBER(D12),ISNUMBER(D11)),(D12-D11)*100,"") -> 50 | P12: =IF(AND(ISNUMBER(F12),ISNUMBER(F11)),F12-F11,"") -> -0.9 | Q12: =IF(COUNTIFS(Wage_Hikes!$A:$A,A12,Wage_Hikes!$D:$D,B12)>0,1,0) -> 0 | R12: =IFERROR(AVERAGEIFS(FX_USDINR!$B:$B,FX_USDINR!$C:$C,B12),"") -> 67.3954 | S12: 0
A13: Wipro | B13: Q4 FY17 | C13: 2017-03-31 | D13: 18.3 | E13: IT Services segment operating margin | F13: 84.8 | G13: 73.1 | H13: 165481 | I13: 16.3 | J13: 1954.6 | K13: 1.7 | L13: S67;S68 | M13: Company datasheet | N13: Identical in two sheets | O13: =IF(AND(TRUE(),ISNUMBER(D13),ISNUMBER(D12)),(D13-D12)*100,"") -> 0 | P13: =IF(AND(ISNUMBER(F13),ISNUMBER(F12)),F13-F12,"") -> 2.9 | Q13: =IF(COUNTIFS(Wage_Hikes!$A:$A,A13,Wage_Hikes!$D:$D,B13)>0,1,0) -> 0 | R13: =IFERROR(AVERAGEIFS(FX_USDINR!$B:$B,FX_USDINR!$C:$C,B13),"") -> 66.9403 | S13: 0
A14: Wipro | B14: Q1 FY18 | C14: 2017-06-30 | D14: 16.8 | E14: IT Services segment operating margin | F14: 82.1 | G14: 72 | H14: 166790 | I14: 15.9 | J14: 1971.7 | K14: 0.3 | L14: S68 | M14: Company datasheet | O14: =IF(AND(TRUE(),ISNUMBER(D14),ISNUMBER(D13)),(D14-D13)*100,"") -> -150 | P14: =IF(AND(ISNUMBER(F14),ISNUMBER(F13)),F14-F13,"") -> -2.7 | Q14: =IF(COUNTIFS(Wage_Hikes!$A:$A,A14,Wage_Hikes!$D:$D,B14)>0,1,0) -> 0 | R14: =IFERROR(AVERAGEIFS(FX_USDINR!$B:$B,FX_USDINR!$C:$C,B14),"") -> 64.4679 | S14: 0
A15: Wipro | B15: Q2 FY18 | C15: 2017-09-30 | D15: 17.3 | E15: IT Services segment operating margin | F15: 82.5 | G15: 72.9 | H15: 163759 | I15: 15.7 | J15: 2013.5 | K15: 0.3 | L15: S68 | M15: Company datasheet | O15: =IF(AND(TRUE(),ISNUMBER(D15),ISNUMBER(D14)),(D15-D14)*100,"") -> 50 | P15: =IF(AND(ISNUMBER(F15),ISNUMBER(F14)),F15-F14,"") -> 0.4 | Q15: =IF(COUNTIFS(Wage_Hikes!$A:$A,A15,Wage_Hikes!$D:$D,B15)>0,1,0) -> 0 | R15: =IFERROR(AVERAGEIFS(FX_USDINR!$B:$B,FX_USDINR!$C:$C,B15),"") -> 64.289933 | S15: 0
A16: Wipro | B16: Q3 FY18 | C16: 2017-12-31 | D16: 14.8 | E16: IT Services segment operating margin | F16: 81.9 | G16: 71 | H16: 162553 | I16: 15.9 | J16: 2013 | K16: 0.9 | L16: S68 | M16: Company datasheet | N16: One-off: customer insolvency; 17.2% normalised | O16: =IF(AND(TRUE(),ISNUMBER(D16),ISNUMBER(D15)),(D16-D15)*100,"") -> -250 | P16: =IF(AND(ISNUMBER(F16),ISNUMBER(F15)),F16-F15,"") -> -0.6 | Q16: =IF(COUNTIFS(Wage_Hikes!$A:$A,A16,Wage_Hikes!$D:$D,B16)>0,1,0) -> 0 | R16: =IFERROR(AVERAGEIFS(FX_USDINR!$B:$B,FX_USDINR!$C:$C,B16),"") -> 64.7079 | S16: 1
A17: Wipro | B17: Q4 FY18 | C17: 2018-03-31 | D17: 14.4 | E17: IT Services segment operating margin | F17: 83.4 | G17: 73.1 | H17: 163827 | I17: 16.6 | J17: 2062 | K17: 1.1 | L17: S68 | M17: Company datasheet | N17: One-offs: customer insolvency + impairment; 16.0% normalised. Restated in S69: 14.6%, headcount 159,923, revenue 2,019.1 | O17: =IF(AND(TRUE(),ISNUMBER(D17),ISNUMBER(D16)),(D17-D16)*100,"") -> -40 | P17: =IF(AND(ISNUMBER(F17),ISNUMBER(F16)),F17-F16,"") -> 1.5 | Q17: =IF(COUNTIFS(Wage_Hikes!$A:$A,A17,Wage_Hikes!$D:$D,B17)>0,1,0) -> 0 | R17: =IFERROR(AVERAGEIFS(FX_USDINR!$B:$B,FX_USDINR!$C:$C,B17),"") -> 64.373567 | S17: 1
A18: Wipro | B18: Q1 FY19 | C18: 2018-06-30 | D18: 17.6 | E18: IT Services segment operating margin | F18: 85.2 | G18: 74.5 | H18: 160846 | I18: 17.1 | J18: 1988.8 | K18: 0.2 | L18: S69 | M18: Company datasheet | N18: Utilisation excludes acquired entities | O18: =IF(AND(TRUE(),ISNUMBER(D18),ISNUMBER(D17)),(D18-D17)*100,"") -> 320 | P18: =IF(AND(ISNUMBER(F18),ISNUMBER(F17)),F18-F17,"") -> 1.8 | Q18: =IF(COUNTIFS(Wage_Hikes!$A:$A,A18,Wage_Hikes!$D:$D,B18)>0,1,0) -> 0 | R18: =IFERROR(AVERAGEIFS(FX_USDINR!$B:$B,FX_USDINR!$C:$C,B18),"") -> 66.990967 | S18: 0
A19: Wipro | B19: Q2 FY19 | C19: 2018-09-30 | D19: 15 | E19: IT Services segment operating margin | F19: 85.5 | G19: 74.4 | H19: 171451 | I19: 17.5 | J19: 2009.5 | K19: 3 | L19: S69;S70 | M19: Company datasheet | N19: One-off depresses margin; Q3 FY19 +480 bps over Q2 reported (S70) | O19: =IF(AND(TRUE(),ISNUMBER(D19),ISNUMBER(D18)),(D19-D18)*100,"") -> -260 | P19: =IF(AND(ISNUMBER(F19),ISNUMBER(F18)),F19-F18,"") -> 0.3 | Q19: =IF(COUNTIFS(Wage_Hikes!$A:$A,A19,Wage_Hikes!$D:$D,B19)>0,1,0) -> 0 | R19: =IFERROR(AVERAGEIFS(FX_USDINR!$B:$B,FX_USDINR!$C:$C,B19),"") -> 70.198767 | S19: 1
A20: Wipro | B20: Q3 FY19 | C20: 2018-12-31 | D20: 19.8 | E20: IT Services segment operating margin | F20: 83.2 | G20: 73.4 | H20: 172379 | I20: 17.9 | J20: 2046.5 | K20: 2.4 | L20: S69;S70 | M20: Company datasheet | O20: =IF(AND(TRUE(),ISNUMBER(D20),ISNUMBER(D19)),(D20-D19)*100,"") -> 480 | P20: =IF(AND(ISNUMBER(F20),ISNUMBER(F19)),F20-F19,"") -> -2.3 | Q20: =IF(COUNTIFS(Wage_Hikes!$A:$A,A20,Wage_Hikes!$D:$D,B20)>0,1,0) -> 0 | R20: =IFERROR(AVERAGEIFS(FX_USDINR!$B:$B,FX_USDINR!$C:$C,B20),"") -> 72.044 | S20: 0
A21: Wipro | B21: Q4 FY19 | C21: 2019-03-31 | D21: 19 | E21: IT Services segment operating margin | F21: 85.4 | G21: 75.4 | H21: 171425 | I21: 17.6 | J21: 2075.5 | K21: 1 | L21: S69 | M21: Company datasheet | O21: =IF(AND(TRUE(),ISNUMBER(D21),ISNUMBER(D20)),(D21-D20)*100,"") -> -80 | P21: =IF(AND(ISNUMBER(F21),ISNUMBER(F20)),F21-F20,"") -> 2.2 | Q21: =IF(COUNTIFS(Wage_Hikes!$A:$A,A21,Wage_Hikes!$D:$D,B21)>0,1,0) -> 0 | R21: =IFERROR(AVERAGEIFS(FX_USDINR!$B:$B,FX_USDINR!$C:$C,B21),"") -> 70.4578 | S21: 0
A22: Wipro | B22: Q1 FY20 | C22: 2019-06-30 | D22: 18.4 | E22: IT Services segment operating margin | F22: 85 | G22: 73.9 | H22: 174850 | I22: 17.6 | J22: 2038.8 | K22: -0.7 | L22: S08 | M22: Company datasheet | O22: =IF(AND(TRUE(),ISNUMBER(D22),ISNUMBER(D21)),(D22-D21)*100,"") -> -60 | P22: =IF(AND(ISNUMBER(F22),ISNUMBER(F21)),F22-F21,"") -> -0.4 | Q22: =IF(COUNTIFS(Wage_Hikes!$A:$A,A22,Wage_Hikes!$D:$D,B22)>0,1,0) -> 0 | R22: =IFERROR(AVERAGEIFS(FX_USDINR!$B:$B,FX_USDINR!$C:$C,B22),"") -> 69.525833 | S22: 0
A23: Wipro | B23: Q2 FY20 | C23: 2019-09-30 | D23: 18.1 | E23: IT Services segment operating margin | F23: 82.1 | G23: 71.4 | H23: 181453 | I23: 17 | J23: 2048.9 | K23: 1.1 | L23: S08 | M23: Company datasheet | O23: =IF(AND(TRUE(),ISNUMBER(D23),ISNUMBER(D22)),(D23-D22)*100,"") -> -30 | P23: =IF(AND(ISNUMBER(F23),ISNUMBER(F22)),F23-F22,"") -> -2.9 | Q23: =IF(COUNTIFS(Wage_Hikes!$A:$A,A23,Wage_Hikes!$D:$D,B23)>0,1,0) -> 0 | R23: =IFERROR(AVERAGEIFS(FX_USDINR!$B:$B,FX_USDINR!$C:$C,B23),"") -> 70.413067 | S23: 0
A24: Wipro | B24: Q3 FY20 | C24: 2019-12-31 | D24: 18.4 | E24: IT Services segment operating margin | F24: 79.6 | G24: 70.2 | H24: 187318 | I24: 15.7 | J24: 2094.8 | K24: 1.8 | L24: S08 | M24: Company datasheet | O24: =IF(AND(TRUE(),ISNUMBER(D24),ISNUMBER(D23)),(D24-D23)*100,"") -> 30 | P24: =IF(AND(ISNUMBER(F24),ISNUMBER(F23)),F24-F23,"") -> -2.5 | Q24: =IF(COUNTIFS(Wage_Hikes!$A:$A,A24,Wage_Hikes!$D:$D,B24)>0,1,0) -> 0 | R24: =IFERROR(AVERAGEIFS(FX_USDINR!$B:$B,FX_USDINR!$C:$C,B24),"") -> 71.219833 | S24: 0
A25: Wipro | B25: Q4 FY20 | C25: 2020-03-31 | D25: 17.6 | E25: IT Services segment operating margin | F25: 82.6 | G25: 73.4 | H25: 182886 | I25: 14.7 | J25: 2073.7 | K25: 0.4 | L25: S08 | M25: Company datasheet | O25: =IF(AND(TRUE(),ISNUMBER(D25),ISNUMBER(D24)),(D25-D24)*100,"") -> -80 | P25: =IF(AND(ISNUMBER(F25),ISNUMBER(F24)),F25-F24,"") -> 3 | Q25: =IF(COUNTIFS(Wage_Hikes!$A:$A,A25,Wage_Hikes!$D:$D,B25)>0,1,0) -> 0 | R25: =IFERROR(AVERAGEIFS(FX_USDINR!$B:$B,FX_USDINR!$C:$C,B25),"") -> 72.452233 | S25: 0
A26: Wipro | B26: Q1 FY21 | C26: 2020-06-30 | D26: 19 | E26: IT Services segment operating margin | F26: 84.5 | G26: 75 | H26: 181804 | I26: 13 | J26: 1921.6 | K26: -7.5 | L26: S08 | M26: Company datasheet | N26: COVID quarter | O26: =IF(AND(TRUE(),ISNUMBER(D26),ISNUMBER(D25)),(D26-D25)*100,"") -> 140 | P26: =IF(AND(ISNUMBER(F26),ISNUMBER(F25)),F26-F25,"") -> 1.9 | Q26: =IF(COUNTIFS(Wage_Hikes!$A:$A,A26,Wage_Hikes!$D:$D,B26)>0,1,0) -> 0 | R26: =IFERROR(AVERAGEIFS(FX_USDINR!$B:$B,FX_USDINR!$C:$C,B26),"") -> 75.844467 | S26: 1
A27: Wipro | B27: Q2 FY21 | C27: 2020-09-30 | D27: 19.2 | E27: IT Services segment operating margin | F27: 86.9 | G27: 76.4 | H27: 185243 | I27: 11 | J27: 1992.4 | K27: 2 | L27: S08 | M27: Company datasheet | O27: =IF(AND(TRUE(),ISNUMBER(D27),ISNUMBER(D26)),(D27-D26)*100,"") -> 20 | P27: =IF(AND(ISNUMBER(F27),ISNUMBER(F26)),F27-F26,"") -> 2.4 | Q27: =IF(COUNTIFS(Wage_Hikes!$A:$A,A27,Wage_Hikes!$D:$D,B27)>0,1,0) -> 0 | R27: =IFERROR(AVERAGEIFS(FX_USDINR!$B:$B,FX_USDINR!$C:$C,B27),"") -> 74.3392 | S27: 0
A28: Wipro | B28: Q3 FY21 | C28: 2020-12-31 | D28: 21.7 | E28: IT Services segment operating margin | F28: 86.3 | G28: 74.8 | H28: 190308 | I28: 11 | J28: 2071 | K28: 3.4 | L28: S07 | M28: Company datasheet | O28: =IF(AND(TRUE(),ISNUMBER(D28),ISNUMBER(D27)),(D28-D27)*100,"") -> 250 | P28: =IF(AND(ISNUMBER(F28),ISNUMBER(F27)),F28-F27,"") -> -0.6 | Q28: =IF(COUNTIFS(Wage_Hikes!$A:$A,A28,Wage_Hikes!$D:$D,B28)>0,1,0) -> 0 | R28: =IFERROR(AVERAGEIFS(FX_USDINR!$B:$B,FX_USDINR!$C:$C,B28),"") -> 73.805133 | S28: 0
A29: Wipro | B29: Q4 FY21 | C29: 2021-03-31 | D29: 21 | E29: IT Services segment operating margin | F29: 86 | G29: 76.7 | H29: 197712 | I29: 12.1 | J29: 2152.4 | K29: 3 | L29: S06 | M29: Company datasheet | O29: =IF(AND(TRUE(),ISNUMBER(D29),ISNUMBER(D28)),(D29-D28)*100,"") -> -70 | P29: =IF(AND(ISNUMBER(F29),ISNUMBER(F28)),F29-F28,"") -> -0.3 | Q29: =IF(COUNTIFS(Wage_Hikes!$A:$A,A29,Wage_Hikes!$D:$D,B29)>0,1,0) -> 1 | R29: =IFERROR(AVERAGEIFS(FX_USDINR!$B:$B,FX_USDINR!$C:$C,B29),"") -> 72.911833 | S29: 0
A30: Wipro | B30: Q1 FY22 | C30: 2021-06-30 | D30: 18.8 | E30: IT Services segment operating margin | F30: 86.8 | G30: 77.7 | H30: 209890 | I30: 15.5 | J30: 2414.5 | K30: 12 | L30: S06 | M30: Company datasheet | N30: Capco acquisition consolidated | O30: =IF(AND(TRUE(),ISNUMBER(D30),ISNUMBER(D29)),(D30-D29)*100,"") -> -220 | P30: =IF(AND(ISNUMBER(F30),ISNUMBER(F29)),F30-F29,"") -> 0.8 | Q30: =IF(COUNTIFS(Wage_Hikes!$A:$A,A30,Wage_Hikes!$D:$D,B30)>0,1,0) -> 1 | R30: =IFERROR(AVERAGEIFS(FX_USDINR!$B:$B,FX_USDINR!$C:$C,B30),"") -> 73.767767 | S30: 0
A31: Wipro | B31: Q2 FY22 | C31: 2021-09-30 | D31: 17.8 | E31: IT Services segment operating margin | F31: 89.2 | G31: 78.1 | H31: 221365 | I31: 20.5 | J31: 2580 | K31: 8.1 | L31: S06 | M31: Company datasheet | O31: =IF(AND(TRUE(),ISNUMBER(D31),ISNUMBER(D30)),(D31-D30)*100,"") -> -100 | P31: =IF(AND(ISNUMBER(F31),ISNUMBER(F30)),F31-F30,"") -> 2.4 | Q31: =IF(COUNTIFS(Wage_Hikes!$A:$A,A31,Wage_Hikes!$D:$D,B31)>0,1,0) -> 1 | R31: =IFERROR(AVERAGEIFS(FX_USDINR!$B:$B,FX_USDINR!$C:$C,B31),"") -> 74.096733 | S31: 0
A32: Wipro | B32: Q3 FY22 | C32: 2021-12-31 | D32: 17.6 | E32: IT Services segment operating margin | F32: 85.8 | G32: 75.6 | H32: 231671 | I32: 22.7 | J32: 2639.7 | K32: 3 | L32: S06 | M32: Company datasheet | O32: =IF(AND(TRUE(),ISNUMBER(D32),ISNUMBER(D31)),(D32-D31)*100,"") -> -20 | P32: =IF(AND(ISNUMBER(F32),ISNUMBER(F31)),F32-F31,"") -> -3.4 | Q32: =IF(COUNTIFS(Wage_Hikes!$A:$A,A32,Wage_Hikes!$D:$D,B32)>0,1,0) -> 0 | R32: =IFERROR(AVERAGEIFS(FX_USDINR!$B:$B,FX_USDINR!$C:$C,B32),"") -> 74.9306 | S32: 0
A33: Wipro | B33: Q4 FY22 | C33: 2022-03-31 | D33: 17 | E33: IT Services segment operating margin | F33: 85.2 | G33: 75.8 | H33: 243128 | I33: 23.8 | J33: 2721.7 | K33: 3.1 | L33: S06 | M33: Company datasheet | O33: =IF(AND(TRUE(),ISNUMBER(D33),ISNUMBER(D32)),(D33-D32)*100,"") -> -60 | P33: =IF(AND(ISNUMBER(F33),ISNUMBER(F32)),F33-F32,"") -> -0.6 | Q33: =IF(COUNTIFS(Wage_Hikes!$A:$A,A33,Wage_Hikes!$D:$D,B33)>0,1,0) -> 0 | R33: =IFERROR(AVERAGEIFS(FX_USDINR!$B:$B,FX_USDINR!$C:$C,B33),"") -> 75.188867 | S33: 0
A34: Wipro | B34: Q1 FY23 | C34: 2022-06-30 | D34: 14.9 | E34: IT Services segment operating margin | F34: 83.8 | H34: 262049 | I34: 23 | J34: 2756.1 | K34: 1.9 | L34: S05 | M34: Company datasheet | O34: =IF(AND(TRUE(),ISNUMBER(D34),ISNUMBER(D33)),(D34-D33)*100,"") -> -210 | P34: =IF(AND(ISNUMBER(F34),ISNUMBER(F33)),F34-F33,"") -> -1.4 | Q34: =IF(COUNTIFS(Wage_Hikes!$A:$A,A34,Wage_Hikes!$D:$D,B34)>0,1,0) -> 0 | R34: =IFERROR(AVERAGEIFS(FX_USDINR!$B:$B,FX_USDINR!$C:$C,B34),"") -> 77.185067 | S34: 0
A35: Wipro | B35: Q2 FY23 | C35: 2022-09-30 | D35: 15.1 | E35: IT Services segment operating margin | F35: 79.8 | H35: 262626 | I35: 22.9 | J35: 2817.4 | K35: 4.1 | L35: S05 | M35: Company datasheet | O35: =IF(AND(TRUE(),ISNUMBER(D35),ISNUMBER(D34)),(D35-D34)*100,"") -> 20 | P35: =IF(AND(ISNUMBER(F35),ISNUMBER(F34)),F35-F34,"") -> -4 | Q35: =IF(COUNTIFS(Wage_Hikes!$A:$A,A35,Wage_Hikes!$D:$D,B35)>0,1,0) -> 1 | R35: =IFERROR(AVERAGEIFS(FX_USDINR!$B:$B,FX_USDINR!$C:$C,B35),"") -> 79.783933 | S35: 0
A36: Wipro | B36: Q3 FY23 | C36: 2022-12-31 | D36: 16.2 | E36: IT Services segment operating margin | F36: 79.7 | H36: 262109 | I36: 21.2 | J36: 2821.4 | K36: 0.6 | L36: S05 | M36: Company datasheet | N36: Value from FY24 datasheet; check original Q3 FY23 datasheet for restatement | O36: =IF(AND(TRUE(),ISNUMBER(D36),ISNUMBER(D35)),(D36-D35)*100,"") -> 110 | P36: =IF(AND(ISNUMBER(F36),ISNUMBER(F35)),F36-F35,"") -> -0.1 | Q36: =IF(COUNTIFS(Wage_Hikes!$A:$A,A36,Wage_Hikes!$D:$D,B36)>0,1,0) -> 0 | R36: =IFERROR(AVERAGEIFS(FX_USDINR!$B:$B,FX_USDINR!$C:$C,B36),"") -> 82.1486 | S36: 0
A37: Wipro | B37: Q4 FY23 | C37: 2023-03-31 | D37: 16.3 | E37: IT Services segment operating margin | F37: 81.7 | H37: 258570 | I37: 19.4 | J37: 2839.5 | K37: -0.7 | L37: S05 | M37: Company datasheet | O37: =IF(AND(TRUE(),ISNUMBER(D37),ISNUMBER(D36)),(D37-D36)*100,"") -> 10 | P37: =IF(AND(ISNUMBER(F37),ISNUMBER(F36)),F37-F36,"") -> 2 | Q37: =IF(COUNTIFS(Wage_Hikes!$A:$A,A37,Wage_Hikes!$D:$D,B37)>0,1,0) -> 0 | R37: =IFERROR(AVERAGEIFS(FX_USDINR!$B:$B,FX_USDINR!$C:$C,B37),"") -> 82.202333 | S37: 0
A38: Wipro | B38: Q1 FY24 | C38: 2023-06-30 | D38: 16 | E38: IT Services segment operating margin | F38: 83.7 | H38: 249758 | I38: 17.3 | J38: 2778.5 | K38: -2.8 | L38: S05 | M38: Company datasheet | O38: =IF(AND(TRUE(),ISNUMBER(D38),ISNUMBER(D37)),(D38-D37)*100,"") -> -30 | P38: =IF(AND(ISNUMBER(F38),ISNUMBER(F37)),F38-F37,"") -> 2 | Q38: =IF(COUNTIFS(Wage_Hikes!$A:$A,A38,Wage_Hikes!$D:$D,B38)>0,1,0) -> 0 | R38: =IFERROR(AVERAGEIFS(FX_USDINR!$B:$B,FX_USDINR!$C:$C,B38),"") -> 82.1638 | S38: 0
A39: Wipro | B39: Q2 FY24 | C39: 2023-09-30 | D39: 16.1 | E39: IT Services segment operating margin | F39: 84.5 | H39: 244707 | I39: 15.5 | J39: 2713.3 | K39: -2 | L39: S05;S04 | M39: Company datasheet | O39: =IF(AND(TRUE(),ISNUMBER(D39),ISNUMBER(D38)),(D39-D38)*100,"") -> 10 | P39: =IF(AND(ISNUMBER(F39),ISNUMBER(F38)),F39-F38,"") -> 0.8 | Q39: =IF(COUNTIFS(Wage_Hikes!$A:$A,A39,Wage_Hikes!$D:$D,B39)>0,1,0) -> 0 | R39: =IFERROR(AVERAGEIFS(FX_USDINR!$B:$B,FX_USDINR!$C:$C,B39),"") -> 82.679567 | S39: 0
A40: Wipro | B40: Q3 FY24 | C40: 2023-12-31 | D40: 16 | E40: IT Services segment operating margin | F40: 84 | H40: 240234 | I40: 14.2 | J40: 2656.1 | K40: -1.7 | L40: S04 | M40: Company datasheet | O40: =IF(AND(TRUE(),ISNUMBER(D40),ISNUMBER(D39)),(D40-D39)*100,"") -> -10 | P40: =IF(AND(ISNUMBER(F40),ISNUMBER(F39)),F40-F39,"") -> -0.5 | Q40: =IF(COUNTIFS(Wage_Hikes!$A:$A,A40,Wage_Hikes!$D:$D,B40)>0,1,0) -> 1 | R40: =IFERROR(AVERAGEIFS(FX_USDINR!$B:$B,FX_USDINR!$C:$C,B40),"") -> 83.2454 | S40: 0
A41: Wipro | B41: Q4 FY24 | C41: 2024-03-31 | D41: 16.4 | E41: IT Services segment operating margin | F41: 86.9 | H41: 232614 | I41: 14.2 | J41: 2657.4 | K41: -0.3 | L41: S03 | M41: Company datasheet | O41: =IF(AND(TRUE(),ISNUMBER(D41),ISNUMBER(D40)),(D41-D40)*100,"") -> 40 | P41: =IF(AND(ISNUMBER(F41),ISNUMBER(F40)),F41-F40,"") -> 2.9 | Q41: =IF(COUNTIFS(Wage_Hikes!$A:$A,A41,Wage_Hikes!$D:$D,B41)>0,1,0) -> 0 | R41: =IFERROR(AVERAGEIFS(FX_USDINR!$B:$B,FX_USDINR!$C:$C,B41),"") -> 83.027267 | S41: 0
A42: Wipro | B42: Q1 FY25 | C42: 2024-06-30 | D42: 16.5 | E42: IT Services segment operating margin | F42: 87.7 | H42: 232911 | I42: 14.1 | J42: 2625.9 | K42: -1 | L42: S03 | M42: Company datasheet | O42: =IF(AND(TRUE(),ISNUMBER(D42),ISNUMBER(D41)),(D42-D41)*100,"") -> 10 | P42: =IF(AND(ISNUMBER(F42),ISNUMBER(F41)),F42-F41,"") -> 0.8 | Q42: =IF(COUNTIFS(Wage_Hikes!$A:$A,A42,Wage_Hikes!$D:$D,B42)>0,1,0) -> 0 | R42: =IFERROR(AVERAGEIFS(FX_USDINR!$B:$B,FX_USDINR!$C:$C,B42),"") -> 83.4147 | S42: 0
A43: Wipro | B43: Q2 FY25 | C43: 2024-09-30 | D43: 16.8 | E43: IT Services segment operating margin | F43: 86.4 | H43: 233889 | I43: 14.5 | J43: 2660.1 | K43: 0.6 | L43: S03 | M43: Company datasheet | O43: =IF(AND(TRUE(),ISNUMBER(D43),ISNUMBER(D42)),(D43-D42)*100,"") -> 30 | P43: =IF(AND(ISNUMBER(F43),ISNUMBER(F42)),F43-F42,"") -> -1.3 | Q43: =IF(COUNTIFS(Wage_Hikes!$A:$A,A43,Wage_Hikes!$D:$D,B43)>0,1,0) -> 1 | R43: =IFERROR(AVERAGEIFS(FX_USDINR!$B:$B,FX_USDINR!$C:$C,B43),"") -> 83.755333 | S43: 0
A44: Wipro | B44: Q3 FY25 | C44: 2024-12-31 | D44: 17.5 | E44: IT Services segment operating margin | F44: 83.5 | H44: 232732 | I44: 15.3 | J44: 2629.1 | K44: 0.1 | L44: S03 | M44: Company datasheet | O44: =IF(AND(TRUE(),ISNUMBER(D44),ISNUMBER(D43)),(D44-D43)*100,"") -> 70 | P44: =IF(AND(ISNUMBER(F44),ISNUMBER(F43)),F44-F43,"") -> -2.9 | Q44: =IF(COUNTIFS(Wage_Hikes!$A:$A,A44,Wage_Hikes!$D:$D,B44)>0,1,0) -> 0 | R44: =IFERROR(AVERAGEIFS(FX_USDINR!$B:$B,FX_USDINR!$C:$C,B44),"") -> 84.4354 | S44: 0
A45: Wipro | B45: Q4 FY25 | C45: 2025-03-31 | D45: 17.5 | E45: IT Services segment operating margin | F45: 84.6 | H45: 233346 | I45: 15 | J45: 2596.5 | K45: -0.8 | L45: S03 | M45: Company datasheet | O45: =IF(AND(TRUE(),ISNUMBER(D45),ISNUMBER(D44)),(D45-D44)*100,"") -> 0 | P45: =IF(AND(ISNUMBER(F45),ISNUMBER(F44)),F45-F44,"") -> 1.1 | Q45: =IF(COUNTIFS(Wage_Hikes!$A:$A,A45,Wage_Hikes!$D:$D,B45)>0,1,0) -> 0 | R45: =IFERROR(AVERAGEIFS(FX_USDINR!$B:$B,FX_USDINR!$C:$C,B45),"") -> 86.616767 | S45: 0
A46: Wipro | B46: Q1 FY26 | C46: 2025-06-30 | D46: 17.3 | E46: IT Services segment operating margin | F46: 85 | H46: 233232 | I46: 15.1 | J46: 2587.4 | K46: -2 | L46: S02 | M46: Company datasheet | O46: =IF(AND(TRUE(),ISNUMBER(D46),ISNUMBER(D45)),(D46-D45)*100,"") -> -20 | P46: =IF(AND(ISNUMBER(F46),ISNUMBER(F45)),F46-F45,"") -> 0.4 | Q46: =IF(COUNTIFS(Wage_Hikes!$A:$A,A46,Wage_Hikes!$D:$D,B46)>0,1,0) -> 0 | R46: =IFERROR(AVERAGEIFS(FX_USDINR!$B:$B,FX_USDINR!$C:$C,B46),"") -> 85.5665 | S46: 0
A47: Wipro | B47: Q2 FY26 | C47: 2025-09-30 | D47: 16.7 | E47: IT Services segment operating margin | F47: 86.4 | H47: 235492 | I47: 14.9 | J47: 2604.3 | K47: 0.3 | L47: S02 | M47: Company datasheet | N47: One-off customer-bankruptcy provision; 17.2% excl. (D1) | O47: =IF(AND(TRUE(),ISNUMBER(D47),ISNUMBER(D46)),(D47-D46)*100,"") -> -60 | P47: =IF(AND(ISNUMBER(F47),ISNUMBER(F46)),F47-F46,"") -> 1.4 | Q47: =IF(COUNTIFS(Wage_Hikes!$A:$A,A47,Wage_Hikes!$D:$D,B47)>0,1,0) -> 0 | R47: =IFERROR(AVERAGEIFS(FX_USDINR!$B:$B,FX_USDINR!$C:$C,B47),"") -> 87.3541 | S47: 1
A48: Wipro | B48: Q3 FY26 | C48: 2025-12-31 | D48: 17.6 | E48: IT Services segment operating margin | F48: 83.1 | H48: 242021 | I48: 14.2 | J48: 2635.4 | K48: 1.4 | L48: S02 | M48: Company datasheet | O48: =IF(AND(TRUE(),ISNUMBER(D48),ISNUMBER(D47)),(D48-D47)*100,"") -> 90 | P48: =IF(AND(ISNUMBER(F48),ISNUMBER(F47)),F48-F47,"") -> -3.3 | Q48: =IF(COUNTIFS(Wage_Hikes!$A:$A,A48,Wage_Hikes!$D:$D,B48)>0,1,0) -> 0 | R48: =IFERROR(AVERAGEIFS(FX_USDINR!$B:$B,FX_USDINR!$C:$C,B48),"") -> 89.082833 | S48: 0
A49: Wipro | B49: Q4 FY26 | C49: 2026-03-31 | D49: 17.3 | E49: IT Services segment operating margin | F49: 83.5 | H49: 242156 | I49: 13.8 | J49: 2651 | K49: 0.2 | L49: S02 | M49: Company datasheet | O49: =IF(AND(TRUE(),ISNUMBER(D49),ISNUMBER(D48)),(D49-D48)*100,"") -> -30 | P49: =IF(AND(ISNUMBER(F49),ISNUMBER(F48)),F49-F48,"") -> 0.4 | Q49: =IF(COUNTIFS(Wage_Hikes!$A:$A,A49,Wage_Hikes!$D:$D,B49)>0,1,0) -> 1 | R49: =IFERROR(AVERAGEIFS(FX_USDINR!$B:$B,FX_USDINR!$C:$C,B49),"") -> 91.488833 | S49: 0
A50: Wipro | B50: Q1 FY27 | C50: 2026-06-30 | D50: 16 | E50: IT Services segment operating margin | F50: 83.6 | H50: 243044 | I50: 13.9 | J50: 2614.5 | K50: -1.2 | L50: S02 | M50: Company datasheet | O50: =IF(AND(TRUE(),ISNUMBER(D50),ISNUMBER(D49)),(D50-D49)*100,"") -> -130 | P50: =IF(AND(ISNUMBER(F50),ISNUMBER(F49)),F50-F49,"") -> 0.1 | Q50: =IF(COUNTIFS(Wage_Hikes!$A:$A,A50,Wage_Hikes!$D:$D,B50)>0,1,0) -> 0 | R50: =IFERROR(AVERAGEIFS(FX_USDINR!$B:$B,FX_USDINR!$C:$C,B50),"") -> 94.658 | S50: 0
A51: Wipro | B51: Q2 FY27 | C51: 2026-09-30 | D51: 16.5 | E51: IT Services segment operating margin | F51: 83.4 | H51: 236328 | I51: 13.8 | J51: 2611.5 | K51: 0 | L51: S02;S38;S31 | M51: Company datasheet | N51: Bloomberg headcount 236,328 agrees (S01) | O51: =IF(AND(TRUE(),ISNUMBER(D51),ISNUMBER(D50)),(D51-D50)*100,"") -> 50 | P51: =IF(AND(ISNUMBER(F51),ISNUMBER(F50)),F51-F50,"") -> -0.2 | Q51: =IF(COUNTIFS(Wage_Hikes!$A:$A,A51,Wage_Hikes!$D:$D,B51)>0,1,0) -> 0 | R51: =IFERROR(AVERAGEIFS(FX_USDINR!$B:$B,FX_USDINR!$C:$C,B51),"") -> 95.604667 | S51: 0
A52: Infosys | B52: Q4 FY19 | C52: 2019-03-31 | D52: 21.5 | E52: Company operating margin (IFRS, USD) | F52: 82.3 | G52: 78.9 | H52: 228123 | J52: 3060 | L52: S73 | M52: Company fact sheet | N52: Attrition reported only on annualised consolidated basis (20.4%) — not used | Q52: =IF(COUNTIFS(Wage_Hikes!$A:$A,A52,Wage_Hikes!$D:$D,B52)>0,1,0) -> 0 | R52: =IFERROR(AVERAGEIFS(FX_USDINR!$B:$B,FX_USDINR!$C:$C,B52),"") -> 70.4578 | S52: 0
A53: Infosys | B53: Q1 FY20 | C53: 2019-06-30 | D53: 20.5 | E53: Company operating margin (IFRS, USD) | F53: 83.1 | L53: S74 | M53: Transcript | N53: CFO and COO statements; no fact sheet collected | O53: =IF(AND(TRUE(),ISNUMBER(D53),ISNUMBER(D52)),(D53-D52)*100,"") -> -100 | P53: =IF(AND(ISNUMBER(F53),ISNUMBER(F52)),F53-F52,"") -> 0.8 | Q53: =IF(COUNTIFS(Wage_Hikes!$A:$A,A53,Wage_Hikes!$D:$D,B53)>0,1,0) -> 0 | R53: =IFERROR(AVERAGEIFS(FX_USDINR!$B:$B,FX_USDINR!$C:$C,B53),"") -> 69.525833 | S53: 0
A54: Infosys | B54: Q2 FY20 | C54: 2019-09-30 | D54: 21.7 | E54: Company operating margin (IFRS, USD) | F54: 84.9 | G54: 81.6 | H54: 236486 | I54: 18.3 | J54: 3210 | L54: S72;S79 | M54: Company fact sheet | N54: Attrition annualised, IT services (not LTM) | O54: =IF(AND(TRUE(),ISNUMBER(D54),ISNUMBER(D53)),(D54-D53)*100,"") -> 120 | P54: =IF(AND(ISNUMBER(F54),ISNUMBER(F53)),F54-F53,"") -> 1.8 | Q54: =IF(COUNTIFS(Wage_Hikes!$A:$A,A54,Wage_Hikes!$D:$D,B54)>0,1,0) -> 0 | R54: =IFERROR(AVERAGEIFS(FX_USDINR!$B:$B,FX_USDINR!$C:$C,B54),"") -> 70.413067 | S54: 0
A55: Infosys | B55: Q3 FY20 | C55: 2019-12-31 | D55: 21.9 | E55: Company operating margin (IFRS, USD) | F55: 84.4 | G55: 80.4 | H55: 243454 | J55: 3243 | L55: S73 | M55: Company fact sheet | N55: Attrition reported only on annualised basis — not used | O55: =IF(AND(TRUE(),ISNUMBER(D55),ISNUMBER(D54)),(D55-D54)*100,"") -> 20 | P55: =IF(AND(ISNUMBER(F55),ISNUMBER(F54)),F55-F54,"") -> -0.5 | Q55: =IF(COUNTIFS(Wage_Hikes!$A:$A,A55,Wage_Hikes!$D:$D,B55)>0,1,0) -> 0 | R55: =IFERROR(AVERAGEIFS(FX_USDINR!$B:$B,FX_USDINR!$C:$C,B55),"") -> 71.219833 | S55: 0
A56: Infosys | B56: Q4 FY20 | C56: 2020-03-31 | D56: 21.1 | E56: Company operating margin (IFRS, USD) | F56: 83.5 | G56: 79 | H56: 242371 | I56: 15.3 | J56: 3197 | L56: S71;S73 | M56: Company fact sheet | N56: Attrition annualised voluntary, IT services | O56: =IF(AND(TRUE(),ISNUMBER(D56),ISNUMBER(D55)),(D56-D55)*100,"") -> -80 | P56: =IF(AND(ISNUMBER(F56),ISNUMBER(F55)),F56-F55,"") -> -0.9 | Q56: =IF(COUNTIFS(Wage_Hikes!$A:$A,A56,Wage_Hikes!$D:$D,B56)>0,1,0) -> 0 | R56: =IFERROR(AVERAGEIFS(FX_USDINR!$B:$B,FX_USDINR!$C:$C,B56),"") -> 72.452233 | S56: 0
A57: Infosys | B57: Q1 FY21 | C57: 2020-06-30 | D57: 22.7 | E57: Company operating margin (IFRS, USD) | F57: 81.2 | G57: 78.2 | H57: 239233 | I57: 11.7 | J57: 3121 | L57: S72 | M57: Company fact sheet | N57: COVID quarter; attrition annualised | O57: =IF(AND(TRUE(),ISNUMBER(D57),ISNUMBER(D56)),(D57-D56)*100,"") -> 160 | P57: =IF(AND(ISNUMBER(F57),ISNUMBER(F56)),F57-F56,"") -> -2.3 | Q57: =IF(COUNTIFS(Wage_Hikes!$A:$A,A57,Wage_Hikes!$D:$D,B57)>0,1,0) -> 0 | R57: =IFERROR(AVERAGEIFS(FX_USDINR!$B:$B,FX_USDINR!$C:$C,B57),"") -> 75.844467 | S57: 1
A58: Infosys | B58: Q2 FY21 | C58: 2020-09-30 | D58: 25.4 | E58: Company operating margin (IFRS, USD) | F58: 83.6 | G58: 80.6 | H58: 240208 | I58: 7.8 | J58: 3312 | L58: S72 | M58: Company fact sheet | N58: Attrition annualised | O58: =IF(AND(TRUE(),ISNUMBER(D58),ISNUMBER(D57)),(D58-D57)*100,"") -> 270 | P58: =IF(AND(ISNUMBER(F58),ISNUMBER(F57)),F58-F57,"") -> 2.4 | Q58: =IF(COUNTIFS(Wage_Hikes!$A:$A,A58,Wage_Hikes!$D:$D,B58)>0,1,0) -> 0 | R58: =IFERROR(AVERAGEIFS(FX_USDINR!$B:$B,FX_USDINR!$C:$C,B58),"") -> 74.3392 | S58: 0
A59: Infosys | B59: Q3 FY21 | C59: 2020-12-31 | D59: 25.4 | E59: Company operating margin (IFRS, USD) | F59: 86.3 | G59: 82.3 | H59: 249312 | I59: 11 | J59: 3516 | L59: S71;S75;S17 | M59: Company fact sheet | N59: Attrition LTM per S75 (S71 shows 10.0% annualised) | O59: =IF(AND(TRUE(),ISNUMBER(D59),ISNUMBER(D58)),(D59-D58)*100,"") -> 0 | P59: =IF(AND(ISNUMBER(F59),ISNUMBER(F58)),F59-F58,"") -> 2.7 | Q59: =IF(COUNTIFS(Wage_Hikes!$A:$A,A59,Wage_Hikes!$D:$D,B59)>0,1,0) -> 0 | R59: =IFERROR(AVERAGEIFS(FX_USDINR!$B:$B,FX_USDINR!$C:$C,B59),"") -> 73.805133 | S59: 0
A60: Infosys | B60: Q4 FY21 | C60: 2021-03-31 | D60: 24.5 | E60: Company operating margin (IFRS, USD) | F60: 87.7 | G60: 82.2 | H60: 259619 | I60: 15.2 | J60: 3613 | L60: S71 | M60: Company fact sheet | N60: Attrition annualised | O60: =IF(AND(TRUE(),ISNUMBER(D60),ISNUMBER(D59)),(D60-D59)*100,"") -> -90 | P60: =IF(AND(ISNUMBER(F60),ISNUMBER(F59)),F60-F59,"") -> 1.4 | Q60: =IF(COUNTIFS(Wage_Hikes!$A:$A,A60,Wage_Hikes!$D:$D,B60)>0,1,0) -> 1 | R60: =IFERROR(AVERAGEIFS(FX_USDINR!$B:$B,FX_USDINR!$C:$C,B60),"") -> 72.911833 | S60: 0
A61: Infosys | B61: Q1 FY22 | C61: 2021-06-30 | D61: 23.7 | E61: Company operating margin (IFRS, USD) | F61: 88.5 | G61: 83.3 | H61: 267953 | I61: 13.9 | J61: 3782 | L61: S42 | M61: Company fact sheet | O61: =IF(AND(TRUE(),ISNUMBER(D61),ISNUMBER(D60)),(D61-D60)*100,"") -> -80 | P61: =IF(AND(ISNUMBER(F61),ISNUMBER(F60)),F61-F60,"") -> 0.8 | Q61: =IF(COUNTIFS(Wage_Hikes!$A:$A,A61,Wage_Hikes!$D:$D,B61)>0,1,0) -> 0 | R61: =IFERROR(AVERAGEIFS(FX_USDINR!$B:$B,FX_USDINR!$C:$C,B61),"") -> 73.767767 | S61: 0
A62: Infosys | B62: Q2 FY22 | C62: 2021-09-30 | D62: 23.6 | E62: Company operating margin (IFRS, USD) | F62: 89.2 | G62: 84.1 | H62: 279617 | I62: 20.1 | J62: 3998 | L62: S75 | M62: Company fact sheet | O62: =IF(AND(TRUE(),ISNUMBER(D62),ISNUMBER(D61)),(D62-D61)*100,"") -> -10 | P62: =IF(AND(ISNUMBER(F62),ISNUMBER(F61)),F62-F61,"") -> 0.7 | Q62: =IF(COUNTIFS(Wage_Hikes!$A:$A,A62,Wage_Hikes!$D:$D,B62)>0,1,0) -> 0 | R62: =IFERROR(AVERAGEIFS(FX_USDINR!$B:$B,FX_USDINR!$C:$C,B62),"") -> 74.096733 | S62: 0
A63: Infosys | B63: Q3 FY22 | C63: 2021-12-31 | D63: 23.5 | E63: Company operating margin (IFRS, USD) | F63: 88.5 | G63: 82.7 | H63: 292067 | I63: 25.5 | J63: 4250 | L63: S75 | M63: Company fact sheet | O63: =IF(AND(TRUE(),ISNUMBER(D63),ISNUMBER(D62)),(D63-D62)*100,"") -> -10 | P63: =IF(AND(ISNUMBER(F63),ISNUMBER(F62)),F63-F62,"") -> -0.7 | Q63: =IF(COUNTIFS(Wage_Hikes!$A:$A,A63,Wage_Hikes!$D:$D,B63)>0,1,0) -> 0 | R63: =IFERROR(AVERAGEIFS(FX_USDINR!$B:$B,FX_USDINR!$C:$C,B63),"") -> 74.9306 | S63: 0
A64: Infosys | B64: Q4 FY22 | C64: 2022-03-31 | D64: 21.5 | E64: Company operating margin (IFRS, USD) | F64: 87 | G64: 80 | H64: 314015 | I64: 27.7 | J64: 4280 | L64: S42;S43 | M64: Company fact sheet | N64: Identical in two fact sheets | O64: =IF(AND(TRUE(),ISNUMBER(D64),ISNUMBER(D63)),(D64-D63)*100,"") -> -200 | P64: =IF(AND(ISNUMBER(F64),ISNUMBER(F63)),F64-F63,"") -> -1.5 | Q64: =IF(COUNTIFS(Wage_Hikes!$A:$A,A64,Wage_Hikes!$D:$D,B64)>0,1,0) -> 0 | R64: =IFERROR(AVERAGEIFS(FX_USDINR!$B:$B,FX_USDINR!$C:$C,B64),"") -> 75.188867 | S64: 0
A65: Infosys | B65: Q1 FY23 | C65: 2022-06-30 | D65: 20 | E65: Company operating margin (IFRS, USD) | F65: 84.7 | G65: 77.6 | H65: 335186 | I65: 28.4 | J65: 4444 | L65: S42;S16 | M65: Company fact sheet | O65: =IF(AND(TRUE(),ISNUMBER(D65),ISNUMBER(D64)),(D65-D64)*100,"") -> -150 | P65: =IF(AND(ISNUMBER(F65),ISNUMBER(F64)),F65-F64,"") -> -2.3 | Q65: =IF(COUNTIFS(Wage_Hikes!$A:$A,A65,Wage_Hikes!$D:$D,B65)>0,1,0) -> 1 | R65: =IFERROR(AVERAGEIFS(FX_USDINR!$B:$B,FX_USDINR!$C:$C,B65),"") -> 77.185067 | S65: 0
A66: Infosys | B66: Q2 FY23 | C66: 2022-09-30 | D66: 21.5 | E66: Company operating margin (IFRS, USD) | F66: 83.6 | G66: 76.6 | H66: 345218 | I66: 27.1 | J66: 4555 | L66: S44 | M66: Company fact sheet | O66: =IF(AND(TRUE(),ISNUMBER(D66),ISNUMBER(D65)),(D66-D65)*100,"") -> 150 | P66: =IF(AND(ISNUMBER(F66),ISNUMBER(F65)),F66-F65,"") -> -1.1 | Q66: =IF(COUNTIFS(Wage_Hikes!$A:$A,A66,Wage_Hikes!$D:$D,B66)>0,1,0) -> 0 | R66: =IFERROR(AVERAGEIFS(FX_USDINR!$B:$B,FX_USDINR!$C:$C,B66),"") -> 79.783933 | S66: 0
A67: Infosys | B67: Q3 FY23 | C67: 2022-12-31 | D67: 21.5 | E67: Company operating margin (IFRS, USD) | F67: 81.7 | G67: 77.1 | H67: 346845 | I67: 24.3 | J67: 4659 | L67: S43;S21 | M67: Company fact sheet | O67: =IF(AND(TRUE(),ISNUMBER(D67),ISNUMBER(D66)),(D67-D66)*100,"") -> 0 | P67: =IF(AND(ISNUMBER(F67),ISNUMBER(F66)),F67-F66,"") -> -1.9 | Q67: =IF(COUNTIFS(Wage_Hikes!$A:$A,A67,Wage_Hikes!$D:$D,B67)>0,1,0) -> 0 | R67: =IFERROR(AVERAGEIFS(FX_USDINR!$B:$B,FX_USDINR!$C:$C,B67),"") -> 82.1486 | S67: 0
A68: Infosys | B68: Q4 FY23 | C68: 2023-03-31 | D68: 21 | E68: Company operating margin (IFRS, USD) | F68: 80 | G68: 76.9 | H68: 343234 | I68: 20.9 | J68: 4554 | L68: S43 | M68: Company fact sheet | O68: =IF(AND(TRUE(),ISNUMBER(D68),ISNUMBER(D67)),(D68-D67)*100,"") -> -50 | P68: =IF(AND(ISNUMBER(F68),ISNUMBER(F67)),F68-F67,"") -> -1.7 | Q68: =IF(COUNTIFS(Wage_Hikes!$A:$A,A68,Wage_Hikes!$D:$D,B68)>0,1,0) -> 0 | R68: =IFERROR(AVERAGEIFS(FX_USDINR!$B:$B,FX_USDINR!$C:$C,B68),"") -> 82.202333 | S68: 0
A69: Infosys | B69: Q1 FY24 | C69: 2023-06-30 | D69: 20.8 | E69: Company operating margin (IFRS, USD) | F69: 81.1 | G69: 78.9 | H69: 336294 | I69: 17.3 | J69: 4617 | L69: S44;S45 | M69: Company fact sheet | O69: =IF(AND(TRUE(),ISNUMBER(D69),ISNUMBER(D68)),(D69-D68)*100,"") -> -20 | P69: =IF(AND(ISNUMBER(F69),ISNUMBER(F68)),F69-F68,"") -> 1.1 | Q69: =IF(COUNTIFS(Wage_Hikes!$A:$A,A69,Wage_Hikes!$D:$D,B69)>0,1,0) -> 0 | R69: =IFERROR(AVERAGEIFS(FX_USDINR!$B:$B,FX_USDINR!$C:$C,B69),"") -> 82.1638 | S69: 0
A70: Infosys | B70: Q2 FY24 | C70: 2023-09-30 | D70: 21.2 | E70: Company operating margin (IFRS, USD) | F70: 81.8 | G70: 80.4 | H70: 328764 | I70: 14.6 | J70: 4718 | L70: S44;S22 | M70: Company fact sheet | O70: =IF(AND(TRUE(),ISNUMBER(D70),ISNUMBER(D69)),(D70-D69)*100,"") -> 40 | P70: =IF(AND(ISNUMBER(F70),ISNUMBER(F69)),F70-F69,"") -> 0.7 | Q70: =IF(COUNTIFS(Wage_Hikes!$A:$A,A70,Wage_Hikes!$D:$D,B70)>0,1,0) -> 0 | R70: =IFERROR(AVERAGEIFS(FX_USDINR!$B:$B,FX_USDINR!$C:$C,B70),"") -> 82.679567 | S70: 0
A71: Infosys | B71: Q3 FY24 | C71: 2023-12-31 | D71: 20.5 | E71: Company operating margin (IFRS, USD) | F71: 82.7 | G71: 81.7 | H71: 322663 | I71: 12.9 | J71: 4663 | L71: S46 | M71: Company fact sheet | O71: =IF(AND(TRUE(),ISNUMBER(D71),ISNUMBER(D70)),(D71-D70)*100,"") -> -70 | P71: =IF(AND(ISNUMBER(F71),ISNUMBER(F70)),F71-F70,"") -> 0.9 | Q71: =IF(COUNTIFS(Wage_Hikes!$A:$A,A71,Wage_Hikes!$D:$D,B71)>0,1,0) -> 1 | R71: =IFERROR(AVERAGEIFS(FX_USDINR!$B:$B,FX_USDINR!$C:$C,B71),"") -> 83.2454 | S71: 0
A72: Infosys | B72: Q4 FY24 | C72: 2024-03-31 | D72: 20.1 | E72: Company operating margin (IFRS, USD) | F72: 83.5 | G72: 82 | H72: 317240 | I72: 12.6 | J72: 4564 | L72: S45;S47 | M72: Company fact sheet | N72: Identical in infosys.com and SEC copies | O72: =IF(AND(TRUE(),ISNUMBER(D72),ISNUMBER(D71)),(D72-D71)*100,"") -> -40 | P72: =IF(AND(ISNUMBER(F72),ISNUMBER(F71)),F72-F71,"") -> 0.8 | Q72: =IF(COUNTIFS(Wage_Hikes!$A:$A,A72,Wage_Hikes!$D:$D,B72)>0,1,0) -> 0 | R72: =IFERROR(AVERAGEIFS(FX_USDINR!$B:$B,FX_USDINR!$C:$C,B72),"") -> 83.027267 | S72: 0
A73: Infosys | B73: Q1 FY25 | C73: 2024-06-30 | D73: 21.1 | E73: Company operating margin (IFRS, USD) | F73: 85.3 | G73: 83.9 | H73: 315332 | I73: 12.7 | J73: 4714 | L73: S45 | M73: Company fact sheet | O73: =IF(AND(TRUE(),ISNUMBER(D73),ISNUMBER(D72)),(D73-D72)*100,"") -> 100 | P73: =IF(AND(ISNUMBER(F73),ISNUMBER(F72)),F73-F72,"") -> 1.8 | Q73: =IF(COUNTIFS(Wage_Hikes!$A:$A,A73,Wage_Hikes!$D:$D,B73)>0,1,0) -> 0 | R73: =IFERROR(AVERAGEIFS(FX_USDINR!$B:$B,FX_USDINR!$C:$C,B73),"") -> 83.4147 | S73: 0
A74: Infosys | B74: Q2 FY25 | C74: 2024-09-30 | D74: 21.1 | E74: Company operating margin (IFRS, USD) | F74: 85.9 | G74: 84.3 | H74: 317788 | I74: 12.9 | J74: 4894 | L74: S13;S46;S19 | M74: Company fact sheet | O74: =IF(AND(TRUE(),ISNUMBER(D74),ISNUMBER(D73)),(D74-D73)*100,"") -> 0 | P74: =IF(AND(ISNUMBER(F74),ISNUMBER(F73)),F74-F73,"") -> 0.6 | Q74: =IF(COUNTIFS(Wage_Hikes!$A:$A,A74,Wage_Hikes!$D:$D,B74)>0,1,0) -> 0 | R74: =IFERROR(AVERAGEIFS(FX_USDINR!$B:$B,FX_USDINR!$C:$C,B74),"") -> 83.755333 | S74: 0
A75: Infosys | B75: Q3 FY25 | C75: 2024-12-31 | D75: 21.3 | E75: Company operating margin (IFRS, USD) | F75: 86 | G75: 83.4 | H75: 323379 | I75: 13.7 | J75: 4939 | L75: S46;S47;S48 | M75: Company fact sheet | O75: =IF(AND(TRUE(),ISNUMBER(D75),ISNUMBER(D74)),(D75-D74)*100,"") -> 20 | P75: =IF(AND(ISNUMBER(F75),ISNUMBER(F74)),F75-F74,"") -> 0.1 | Q75: =IF(COUNTIFS(Wage_Hikes!$A:$A,A75,Wage_Hikes!$D:$D,B75)>0,1,0) -> 0 | R75: =IFERROR(AVERAGEIFS(FX_USDINR!$B:$B,FX_USDINR!$C:$C,B75),"") -> 84.4354 | S75: 0
A76: Infosys | B76: Q4 FY25 | C76: 2025-03-31 | D76: 21 | E76: Company operating margin (IFRS, USD) | F76: 84.9 | G76: 81.9 | H76: 323578 | I76: 14.1 | L76: S47;S15 | M76: Company fact sheet | O76: =IF(AND(TRUE(),ISNUMBER(D76),ISNUMBER(D75)),(D76-D75)*100,"") -> -30 | P76: =IF(AND(ISNUMBER(F76),ISNUMBER(F75)),F76-F75,"") -> -1.1 | Q76: =IF(COUNTIFS(Wage_Hikes!$A:$A,A76,Wage_Hikes!$D:$D,B76)>0,1,0) -> 1 | R76: =IFERROR(AVERAGEIFS(FX_USDINR!$B:$B,FX_USDINR!$C:$C,B76),"") -> 86.616767 | S76: 0
A77: Infosys | B77: Q1 FY26 | C77: 2025-06-30 | D77: 20.8 | E77: Company operating margin (IFRS, USD) | F77: 85.2 | G77: 82.7 | H77: 323788 | I77: 14.4 | J77: 4941 | L77: S12;S13;S20 | M77: Company fact sheet | O77: =IF(AND(TRUE(),ISNUMBER(D77),ISNUMBER(D76)),(D77-D76)*100,"") -> -20 | P77: =IF(AND(ISNUMBER(F77),ISNUMBER(F76)),F77-F76,"") -> 0.3 | Q77: =IF(COUNTIFS(Wage_Hikes!$A:$A,A77,Wage_Hikes!$D:$D,B77)>0,1,0) -> 1 | R77: =IFERROR(AVERAGEIFS(FX_USDINR!$B:$B,FX_USDINR!$C:$C,B77),"") -> 85.5665 | S77: 0
A78: Infosys | B78: Q2 FY26 | C78: 2025-09-30 | D78: 21 | E78: Company operating margin (IFRS, USD) | F78: 85.1 | G78: 82.2 | H78: 331991 | I78: 14.3 | J78: 5076 | L78: S13;S48 | M78: Company fact sheet | O78: =IF(AND(TRUE(),ISNUMBER(D78),ISNUMBER(D77)),(D78-D77)*100,"") -> 20 | P78: =IF(AND(ISNUMBER(F78),ISNUMBER(F77)),F78-F77,"") -> -0.1 | Q78: =IF(COUNTIFS(Wage_Hikes!$A:$A,A78,Wage_Hikes!$D:$D,B78)>0,1,0) -> 0 | R78: =IFERROR(AVERAGEIFS(FX_USDINR!$B:$B,FX_USDINR!$C:$C,B78),"") -> 87.3541 | S78: 0
A79: Infosys | B79: Q3 FY26 | C79: 2025-12-31 | D79: 18.4 | E79: Company operating margin (IFRS, USD) | F79: 84.1 | G79: 80 | H79: 337034 | I79: 12.3 | J79: 5099 | L79: S48 | M79: Company fact sheet | N79: One-off: New Labour Codes; 21.2% excluding it | O79: =IF(AND(TRUE(),ISNUMBER(D79),ISNUMBER(D78)),(D79-D78)*100,"") -> -260 | P79: =IF(AND(ISNUMBER(F79),ISNUMBER(F78)),F79-F78,"") -> -1 | Q79: =IF(COUNTIFS(Wage_Hikes!$A:$A,A79,Wage_Hikes!$D:$D,B79)>0,1,0) -> 0 | R79: =IFERROR(AVERAGEIFS(FX_USDINR!$B:$B,FX_USDINR!$C:$C,B79),"") -> 89.082833 | S79: 1
A80: Infosys | B80: Q4 FY26 | C80: 2026-03-31 | D80: 20.9 | E80: Company operating margin (IFRS, USD) | F80: 83 | G80: 79.7 | H80: 328594 | I80: 12.6 | J80: 5040 | L80: S12 | M80: Company fact sheet | N80: 20.9% USD table vs 21.0% INR table | O80: =IF(AND(TRUE(),ISNUMBER(D80),ISNUMBER(D79)),(D80-D79)*100,"") -> 250 | P80: =IF(AND(ISNUMBER(F80),ISNUMBER(F79)),F80-F79,"") -> -1.1 | Q80: =IF(COUNTIFS(Wage_Hikes!$A:$A,A80,Wage_Hikes!$D:$D,B80)>0,1,0) -> 0 | R80: =IFERROR(AVERAGEIFS(FX_USDINR!$B:$B,FX_USDINR!$C:$C,B80),"") -> 91.488833 | S80: 0
A81: Infosys | B81: Q1 FY27 | C81: 2026-06-30 | D81: 21.1 | E81: Company operating margin (IFRS, USD) | F81: 84.9 | G81: 82.1 | H81: 328062 | I81: 13 | J81: 5082 | L81: S12;S14 | M81: Company fact sheet | O81: =IF(AND(TRUE(),ISNUMBER(D81),ISNUMBER(D80)),(D81-D80)*100,"") -> 20 | P81: =IF(AND(ISNUMBER(F81),ISNUMBER(F80)),F81-F80,"") -> 1.9 | Q81: =IF(COUNTIFS(Wage_Hikes!$A:$A,A81,Wage_Hikes!$D:$D,B81)>0,1,0) -> 0 | R81: =IFERROR(AVERAGEIFS(FX_USDINR!$B:$B,FX_USDINR!$C:$C,B81),"") -> 94.658 | S81: 0
A82: TCS | B82: Q4 FY22 | C82: 2022-03-31 | D82: 25 | E82: Company operating margin | H82: 592195 | I82: 17.4 | J82: 6696 | L82: S49;S108 | M82: Company fact sheet | N82: Utilisation not disclosed. | Q82: =IF(COUNTIFS(Wage_Hikes!$A:$A,A82,Wage_Hikes!$D:$D,B82)>0,1,0) -> 0 | R82: =IFERROR(AVERAGEIFS(FX_USDINR!$B:$B,FX_USDINR!$C:$C,B82),"") -> 75.188867 | S82: 0
A83: TCS | B83: Q1 FY23 | C83: 2022-06-30 | D83: 23.1 | E83: Company operating margin | H83: 606331 | I83: 19.7 | J83: 6780 | L83: S49;S109 | M83: Company fact sheet | N83: Utilisation not disclosed. | O83: =IF(AND(TRUE(),ISNUMBER(D83),ISNUMBER(D82)),(D83-D82)*100,"") -> -190 | P83: =IF(AND(ISNUMBER(F83),ISNUMBER(F82)),F83-F82,"") | Q83: =IF(COUNTIFS(Wage_Hikes!$A:$A,A83,Wage_Hikes!$D:$D,B83)>0,1,0) -> 0 | R83: =IFERROR(AVERAGEIFS(FX_USDINR!$B:$B,FX_USDINR!$C:$C,B83),"") -> 77.185067 | S83: 0
A84: TCS | B84: Q2 FY23 | C84: 2022-09-30 | D84: 24 | E84: Company operating margin | H84: 616171 | I84: 21.5 | J84: 6877 | L84: S49;S110 | M84: Company fact sheet | N84: Utilisation not disclosed. Attrition from news report; LTM basis not stated. | O84: =IF(AND(TRUE(),ISNUMBER(D84),ISNUMBER(D83)),(D84-D83)*100,"") -> 90 | P84: =IF(AND(ISNUMBER(F84),ISNUMBER(F83)),F84-F83,"") | Q84: =IF(COUNTIFS(Wage_Hikes!$A:$A,A84,Wage_Hikes!$D:$D,B84)>0,1,0) -> 0 | R84: =IFERROR(AVERAGEIFS(FX_USDINR!$B:$B,FX_USDINR!$C:$C,B84),"") -> 79.783933 | S84: 0
A85: TCS | B85: Q3 FY23 | C85: 2022-12-31 | D85: 24.5 | E85: Company operating margin | H85: 613974 | I85: 21.3 | J85: 7075 | L85: S49;S50;S111 | M85: Company fact sheet | N85: Utilisation not disclosed. | O85: =IF(AND(TRUE(),ISNUMBER(D85),ISNUMBER(D84)),(D85-D84)*100,"") -> 50 | P85: =IF(AND(ISNUMBER(F85),ISNUMBER(F84)),F85-F84,"") | Q85: =IF(COUNTIFS(Wage_Hikes!$A:$A,A85,Wage_Hikes!$D:$D,B85)>0,1,0) -> 0 | R85: =IFERROR(AVERAGEIFS(FX_USDINR!$B:$B,FX_USDINR!$C:$C,B85),"") -> 82.1486 | S85: 0
A86: TCS | B86: Q4 FY23 | C86: 2023-03-31 | D86: 24.5 | E86: Company operating margin | H86: 614795 | I86: 20.1 | J86: 7195 | L86: S49;S50 | M86: Company fact sheet | N86: Utilisation not disclosed. | O86: =IF(AND(TRUE(),ISNUMBER(D86),ISNUMBER(D85)),(D86-D85)*100,"") -> 0 | P86: =IF(AND(ISNUMBER(F86),ISNUMBER(F85)),F86-F85,"") | Q86: =IF(COUNTIFS(Wage_Hikes!$A:$A,A86,Wage_Hikes!$D:$D,B86)>0,1,0) -> 0 | R86: =IFERROR(AVERAGEIFS(FX_USDINR!$B:$B,FX_USDINR!$C:$C,B86),"") -> 82.202333 | S86: 0
A87: TCS | B87: Q1 FY24 | C87: 2023-06-30 | D87: 23.2 | E87: Company operating margin | H87: 615318 | I87: 17.8 | J87: 7226 | L87: S50;S112 | M87: Company fact sheet | N87: Utilisation not disclosed. | O87: =IF(AND(TRUE(),ISNUMBER(D87),ISNUMBER(D86)),(D87-D86)*100,"") -> -130 | P87: =IF(AND(ISNUMBER(F87),ISNUMBER(F86)),F87-F86,"") | Q87: =IF(COUNTIFS(Wage_Hikes!$A:$A,A87,Wage_Hikes!$D:$D,B87)>0,1,0) -> 0 | R87: =IFERROR(AVERAGEIFS(FX_USDINR!$B:$B,FX_USDINR!$C:$C,B87),"") -> 82.1638 | S87: 0
A88: TCS | B88: Q2 FY24 | C88: 2023-09-30 | D88: 24.3 | E88: Company operating margin | H88: 608985 | I88: 14.9 | J88: 7210 | L88: S50;S113 | M88: Company fact sheet | N88: Utilisation not disclosed. | O88: =IF(AND(TRUE(),ISNUMBER(D88),ISNUMBER(D87)),(D88-D87)*100,"") -> 110 | P88: =IF(AND(ISNUMBER(F88),ISNUMBER(F87)),F88-F87,"") | Q88: =IF(COUNTIFS(Wage_Hikes!$A:$A,A88,Wage_Hikes!$D:$D,B88)>0,1,0) -> 0 | R88: =IFERROR(AVERAGEIFS(FX_USDINR!$B:$B,FX_USDINR!$C:$C,B88),"") -> 82.679567 | S88: 0
A89: TCS | B89: Q3 FY24 | C89: 2023-12-31 | D89: 25 | E89: Company operating margin | H89: 603305 | I89: 13.3 | J89: 7281 | L89: S50 | M89: Company fact sheet | N89: Utilisation not disclosed. Excludes legal-claim settlement | O89: =IF(AND(TRUE(),ISNUMBER(D89),ISNUMBER(D88)),(D89-D88)*100,"") -> 70 | P89: =IF(AND(ISNUMBER(F89),ISNUMBER(F88)),F89-F88,"") | Q89: =IF(COUNTIFS(Wage_Hikes!$A:$A,A89,Wage_Hikes!$D:$D,B89)>0,1,0) -> 0 | R89: =IFERROR(AVERAGEIFS(FX_USDINR!$B:$B,FX_USDINR!$C:$C,B89),"") -> 83.2454 | S89: 1
A90: TCS | B90: Q4 FY24 | C90: 2024-03-31 | D90: 26 | E90: Company operating margin | H90: 601546 | I90: 12.5 | J90: 7363 | L90: S51;S114 | M90: Company fact sheet | N90: Utilisation not disclosed. | O90: =IF(AND(TRUE(),ISNUMBER(D90),ISNUMBER(D89)),(D90-D89)*100,"") -> 100 | P90: =IF(AND(ISNUMBER(F90),ISNUMBER(F89)),F90-F89,"") | Q90: =IF(COUNTIFS(Wage_Hikes!$A:$A,A90,Wage_Hikes!$D:$D,B90)>0,1,0) -> 0 | R90: =IFERROR(AVERAGEIFS(FX_USDINR!$B:$B,FX_USDINR!$C:$C,B90),"") -> 83.027267 | S90: 0
A91: TCS | B91: Q1 FY25 | C91: 2024-06-30 | D91: 24.7 | E91: Company operating margin | H91: 606998 | I91: 12.1 | J91: 7505 | L91: S51;S63;S115 | M91: Company fact sheet | N91: Utilisation not disclosed. | O91: =IF(AND(TRUE(),ISNUMBER(D91),ISNUMBER(D90)),(D91-D90)*100,"") -> -130 | P91: =IF(AND(ISNUMBER(F91),ISNUMBER(F90)),F91-F90,"") | Q91: =IF(COUNTIFS(Wage_Hikes!$A:$A,A91,Wage_Hikes!$D:$D,B91)>0,1,0) -> 1 | R91: =IFERROR(AVERAGEIFS(FX_USDINR!$B:$B,FX_USDINR!$C:$C,B91),"") -> 83.4147 | S91: 0
A92: TCS | B92: Q2 FY25 | C92: 2024-09-30 | D92: 24.1 | E92: Company operating margin | H92: 612724 | I92: 12.3 | J92: 7670 | L92: S51;S63;S116 | M92: Company fact sheet | N92: Utilisation not disclosed. | O92: =IF(AND(TRUE(),ISNUMBER(D92),ISNUMBER(D91)),(D92-D91)*100,"") -> -60 | P92: =IF(AND(ISNUMBER(F92),ISNUMBER(F91)),F92-F91,"") | Q92: =IF(COUNTIFS(Wage_Hikes!$A:$A,A92,Wage_Hikes!$D:$D,B92)>0,1,0) -> 0 | R92: =IFERROR(AVERAGEIFS(FX_USDINR!$B:$B,FX_USDINR!$C:$C,B92),"") -> 83.755333 | S92: 0
A93: TCS | B93: Q3 FY25 | C93: 2024-12-31 | D93: 24.5 | E93: Company operating margin | H93: 607354 | I93: 13 | J93: 7539 | L93: S51;S63;S117 | M93: Company fact sheet | N93: Utilisation not disclosed. | O93: =IF(AND(TRUE(),ISNUMBER(D93),ISNUMBER(D92)),(D93-D92)*100,"") -> 40 | P93: =IF(AND(ISNUMBER(F93),ISNUMBER(F92)),F93-F92,"") | Q93: =IF(COUNTIFS(Wage_Hikes!$A:$A,A93,Wage_Hikes!$D:$D,B93)>0,1,0) -> 0 | R93: =IFERROR(AVERAGEIFS(FX_USDINR!$B:$B,FX_USDINR!$C:$C,B93),"") -> 84.4354 | S93: 0
A94: TCS | B94: Q4 FY25 | C94: 2025-03-31 | D94: 24.2 | E94: Company operating margin | H94: 607979 | I94: 13.3 | J94: 7465 | L94: S51;S63 | M94: Company fact sheet | N94: Utilisation not disclosed. | O94: =IF(AND(TRUE(),ISNUMBER(D94),ISNUMBER(D93)),(D94-D93)*100,"") -> -30 | P94: =IF(AND(ISNUMBER(F94),ISNUMBER(F93)),F94-F93,"") | Q94: =IF(COUNTIFS(Wage_Hikes!$A:$A,A94,Wage_Hikes!$D:$D,B94)>0,1,0) -> 0 | R94: =IFERROR(AVERAGEIFS(FX_USDINR!$B:$B,FX_USDINR!$C:$C,B94),"") -> 86.616767 | S94: 0
... A100: TCS | B100: Q2 FY27 | C100: 2026-09-30 | D100: 24 | E100: Company operating margin | H100: 598056 | I100: 13.3 | J100: 7642 | L100: S10 | M100: Company fact sheet | N100: Utilisation not disclosed. CFO: invested in higher bench (S36) Attrition reported as 'voluntary LTM' from Q2 FY26. | O100: =IF(AND(TRUE(),ISNUMBER(D100),ISNUMBER(D99)),(D100-D99)*100,"") -> 0 | P100: =IF(AND(ISNUMBER(F100),ISNUMBER(F99)),F100-F99,"") | Q100: =IF(COUNTIFS(Wage_Hikes!$A:$A,A100,Wage_Hikes!$D:$D,B100)>0,1,0) -> 0 | R100: =IFERROR(AVERAGEIFS(FX_USDINR!$B:$B,FX_USDINR!$C:$C,B100),"") -> 95.604667 | S100: 0
A101: HCLTech | B101: Q2 FY25 | C101: 2024-09-30 | D101: 18.6 | E101: Company EBIT margin, incl. restructuring (INR) | H101: 218621 | I101: 12.9 | L101: S52 | M101: Company investor release | N101: Utilisation not disclosed. IT&BS segment 17.6% | Q101: =IF(COUNTIFS(Wage_Hikes!$A:$A,A101,Wage_Hikes!$D:$D,B101)>0,1,0) -> 0 | R101: =IFERROR(AVERAGEIFS(FX_USDINR!$B:$B,FX_USDINR!$C:$C,B101),"") -> 83.755333 | S101: 0
A102: HCLTech | B102: Q3 FY25 | C102: 2024-12-31 | D102: 19.5 | E102: Company EBIT margin, incl. restructuring (INR) | H102: 220755 | I102: 13.2 | L102: S52;S54 | M102: Company investor release | N102: Utilisation not disclosed. IT&BS segment 17.2% | O102: =IF(AND(TRUE(),ISNUMBER(D102),ISNUMBER(D101)),(D102-D101)*100,"") -> 90 | P102: =IF(AND(ISNUMBER(F102),ISNUMBER(F101)),F102-F101,"") | Q102: =IF(COUNTIFS(Wage_Hikes!$A:$A,A102,Wage_Hikes!$D:$D,B102)>0,1,0) -> 0 | R102: =IFERROR(AVERAGEIFS(FX_USDINR!$B:$B,FX_USDINR!$C:$C,B102),"") -> 84.4354 | S102: 0
A103: HCLTech | B103: Q4 FY25 | C103: 2025-03-31 | D103: 18 | E103: Company EBIT margin, incl. restructuring (INR) | H103: 223420 | I103: 13 | L103: S52;S53;S54 | M103: Company investor release | N103: Utilisation not disclosed. 18.0% INR vs 17.9% USD chart | O103: =IF(AND(TRUE(),ISNUMBER(D103),ISNUMBER(D102)),(D103-D102)*100,"") -> -150 | P103: =IF(AND(ISNUMBER(F103),ISNUMBER(F102)),F103-F102,"") | Q103: =IF(COUNTIFS(Wage_Hikes!$A:$A,A103,Wage_Hikes!$D:$D,B103)>0,1,0) -> 0 | R103: =IFERROR(AVERAGEIFS(FX_USDINR!$B:$B,FX_USDINR!$C:$C,B103),"") -> 86.616767 | S103: 0
A104: HCLTech | B104: Q1 FY26 | C104: 2025-06-30 | D104: 16.3 | E104: Company EBIT margin, incl. restructuring (INR) | H104: 223151 | I104: 12.8 | L104: S52;S53;S26 | M104: Company investor release | N104: Utilisation not disclosed. IT&BS segment 15.1% | O104: =IF(AND(TRUE(),ISNUMBER(D104),ISNUMBER(D103)),(D104-D103)*100,"") -> -170 | P104: =IF(AND(ISNUMBER(F104),ISNUMBER(F103)),F104-F103,"") | Q104: =IF(COUNTIFS(Wage_Hikes!$A:$A,A104,Wage_Hikes!$D:$D,B104)>0,1,0) -> 0 | R104: =IFERROR(AVERAGEIFS(FX_USDINR!$B:$B,FX_USDINR!$C:$C,B104),"") -> 85.5665 | S104: 0
A105: HCLTech | B105: Q2 FY26 | C105: 2025-09-30 | D105: 17.5 | E105: Company EBIT margin, incl. restructuring (INR) | H105: 226640 | I105: 12.6 | L105: S11;S52;S53 | M105: Company investor release | N105: Utilisation not disclosed. Incl. 55 bps restructuring (18.0% excl.); IT&BS 16.3% | O105: =IF(AND(TRUE(),ISNUMBER(D105),ISNUMBER(D104)),(D105-D104)*100,"") -> 120 | P105: =IF(AND(ISNUMBER(F105),ISNUMBER(F104)),F105-F104,"") | Q105: =IF(COUNTIFS(Wage_Hikes!$A:$A,A105,Wage_Hikes!$D:$D,B105)>0,1,0) -> 0 | R105: =IFERROR(AVERAGEIFS(FX_USDINR!$B:$B,FX_USDINR!$C:$C,B105),"") -> 87.3541 | S105: 1
...

Sheet Wage_Hikes
A1: Quarter in which each salary hike first hits the P&L. Wipro and Infosys FY15–FY20 and TCS FY22–FY24 cycles not yet sourced (DQ19). Quarterly_Panel column Q flags these quarters by formula.
A3: firm | B3: hike_cycle | C3: effective_date | D3: first_quarter_of_impact | E3: scope | F3: source_id | G3: note
A4: Wipro | B4: FY21 | C4: 2021-01-01 | D4: Q4 FY21 | E4: Bands B3 and below | F4: S96 | G4: Referenced as 'previously announced for these bands in January 2021'
A5: Wipro | B5: FY22 | C5: 2021-06-01 | D5: Q1 FY22 | E5: Manager level and above | F5: S96
A6: Wipro | B6: FY22 | C6: 2021-09-01 | D6: Q2 FY22 | E6: Bands B3 and below (about 80% of workforce) | F6: S96 | G6: Second hike in 2021
A7: Wipro | B7: FY23 | C7: 2022-09-01 | D7: Q2 FY23 | E7: Broad | F7: S95 | G7: CFO: 'last salary increase in September of last year' (said July 2023); day not stated
A8: Wipro | B8: FY24 | C8: 2023-12-01 | D8: Q3 FY24 | E8: Eligible employees | F8: S93 | G8: Originally due September 2023
A9: Wipro | B9: FY25 | C9: 2024-09-01 | D9: Q2 FY25 | E9: Eligible employees | F9: S92
A10: Wipro | B10: FY26 | C10: 2026-03-01 | D10: Q4 FY26 | E10: Eligible employees (merit salary increase) | F10: S94 | G10: First hike in 18 months; full-quarter effect from Q1 FY27
A11: Infosys | B11: FY21 | C11: 2021-01-01 | D11: Q4 FY21 | E11: All employees | F11: S104
A12: Infosys | B12: FY23 | C12: 2022-04-01 | D12: Q1 FY23 | E12: Broad | F12: S16 | G12: Date inferred from CFO margin walk ('1.6% due to salary increases' in Q1 FY23); exact day not stated
A13: Infosys | B13: FY24 | C13: 2023-11-01 | D13: Q3 FY24 | E13: Broad | F13: S103 | G13: 'last raised its salaries in November 2023'
A14: Infosys | B14: FY25 | C14: 2025-01-01 | D14: Q4 FY25 | E14: Phase 1 | F14: S102;S103
A15: Infosys | B15: FY25 | C15: 2025-04-01 | D15: Q1 FY26 | E15: Phase 2 | F15: S102 | G15: CFO; Q1 FY26 walk shows −100 bps compensation (S20)
A16: Infosys | B16: FY27 | C16: 2026-10-01 | D16: Q3 FY27 | E16: Most employees | F16: S101 | G16: After panel end
A17: Infosys | B17: FY27 | C17: 2027-01-01 | D17: Q4 FY27 | E17: Senior employees | F17: S101 | G17: After panel end
A18: TCS | B18: FY25 | C18: 2024-04-01 | D18: Q1 FY25 | E18: Broad | F18: S99
A19: TCS | B19: FY26 | C19: 2025-09-01 | D19: Q2 FY26 | E19: About 80% of workforce | F19: S97;S100;S84 | G19: Deferred from April; CFO: one month of impact in Q2, full quarter in Q3
A20: TCS | B20: FY27 | C20: 2026-04-01 | D20: Q1 FY27 | E20: All eligible employees | F20: S98;S100;S85 | G20: CFO: 170 bps margin impact

Sheet FX_USDINR
A1: Source S91: US Federal Reserve G.5 (via FRED, series EXINUS) — monthly average of daily noon buying rates in New York, rupees per US dollar. Quarterly averages are computed in Quarterly_Panel column R (AVERAGEIFS).
A3: month | B3: usd_inr_monthly_avg | C3: fiscal_quarter
A4: 2014-01-01 | B4: 62.1057 | C4: Q4 FY14
A5: 2014-02-01 | B5: 62.1642 | C5: Q4 FY14
A6: 2014-03-01 | B6: 60.9476 | C6: Q4 FY14
A7: 2014-04-01 | B7: 60.3464 | C7: Q1 FY15
A8: 2014-05-01 | B8: 59.2843 | C8: Q1 FY15
A9: 2014-06-01 | B9: 59.7367 | C9: Q1 FY15
A10: 2014-07-01 | B10: 60.0956 | C10: Q2 FY15
A11: 2014-08-01 | B11: 60.8738 | C11: Q2 FY15
A12: 2014-09-01 | B12: 60.8976 | C12: Q2 FY15
A13: 2014-10-01 | B13: 61.3668 | C13: Q3 FY15
A14: 2014-11-01 | B14: 61.6828 | C14: Q3 FY15
A15: 2014-12-01 | B15: 62.7071 | C15: Q3 FY15
... A156: 2026-09-01 | B156: 95.5124 | C156: Q2 FY27

Sheet TCS_Commentary
A1: TCS does not publish utilisation. This log records what management said about utilisation, bench and capacity each quarter, coded only as stated (no inference).
A3: quarter | B3: call_date | C3: topic | D3: statement (quoted) | E3: speaker | F3: source_id | G3: coded_direction | H3: policy_period
A4: Q4 FY25 | B4: 2025-04-10 | C4: Utilisation | D4: "we focused on improving utilization, productivity and realization" (not quantified) | E4: Samir Seksaria (CFO) | F4: S23 | G4: Lever named | H4: Pre-policy
A5: Q1 FY26 | B5: 2025-07-10 | C5: Utilisation | D5: "The demand contraction during the quarter had an impact on our utilization" | E5: Samir Seksaria (CFO) | F5: S105 | G5: Utilisation down | H5: Policy quarter (cap from 12 Jun 2025)
A6: Q1 FY26 | B6: 2025-07-10 | C6: Capacity | D6: "leads to us carrying excess capacity or additional capacity" | E6: Samir Seksaria (CFO) | F6: S105 | G6: Excess capacity | H6: Policy quarter
A7: Q2 FY26 | B7: 2025-10-09 | C7: Bench | D7: "there has been involuntary attrition as part of regular ongoing efforts pertaining to performance and bench policies" | E7: Sudeep Kunnumal (CHRO) | F7: S84 | G7: Bench enforcement | H7: Post-policy
A8: Q2 FY26 | B8: 2025-10-09 | C8: Restructuring | D8: "We have released 1% of our workforce, mainly mid and senior level"; ₹1,135 crore severance | E8: Sudeep Kunnumal (CHRO) | F8: S84 | G8: Headcount cut | H8: Confounder for the before/after test
A9: Q2 FY26 | B9: 2025-10-09 | C9: Margin | D9: Pyramid rebalancing +40 bps, operating efficiency +20 bps | E9: Samir Seksaria (CFO) | F9: S84 | G9: Efficiency up | H9: Post-policy
A10: Q3 FY26 | B10: 2026-01-12 | C10: Restructuring | D10: "in this quarter, we released approximately 1,800 people" | E10: Sudeep Kunnumal (CHRO) | F10: S106 | G10: Headcount cut | H10: Post-policy
A11: Q3 FY26 | B11: 2026-01-12 | C11: Margin | D11: Productivity, pyramid and other operational efficiencies +80 bps | E11: Samir Seksaria (CFO) | F11: S106 | G11: Efficiency up | H11: Post-policy
A12: Q4 FY26 | B12: 2026-04-09 | C12: Capacity | D12: "higher external consultants' cost of 40 basis points" | E12: Samir Seksaria (CFO) | F12: S107 | G12: External capacity up | H12: Post-policy
A13: Q1 FY27 | B13: 2026-07-09 | C13: Utilisation | D13: Not discussed; wage increments −170 bps | E13: Samir Seksaria (CFO) | F13: S85 | G13: Not stated | H13: Post-policy
A14: Q2 FY27 | B14: 2026-10-08 | C14: Bench | D14: "we have invested in a higher bench and increased hiring of subcontractors" | E14: Samir Seksaria (CFO) | F14: S86 | G14: Bench up | H14: Post-policy: reversal
A15: Q2 FY27 | B15: 2026-10-08 | C15: Utilisation | D15: "driving better productivity and driving better utilization would be on our radar" | E15: Samir Seksaria (CFO) | F15: S86 | G15: Lever named | H15: Post-policy

Sheet Margin_Walks
A1: walk_id | B1: firm | C1: quarter | D1: total_margin_change_bps | E1: util_attributed_bps | F1: tier | G1: util_level_after_pct | H1: util_change_pts | I1: bps_per_util_point | J1: driver_wording (quoted) | K1: speaker | L1: source_id | M1: note
A2: MW01 | B2: Infosys | C2: Q1 FY23 | D2: -150 | E2: -40 | F2: A | G2: 84.7 | H2: -2.3 | I2: =IF(AND(ISNUMBER(E2),ISNUMBER(H2),H2<>0),E2/H2,"") -> 17.391304 | J2: "0.4% due to drop in utilization as we create capacity for future"; "40 basis points because of utilization on margins" | K2: Nilanjan Roy (CFO) | L2: S16;S42 | M2: Utilisation excl. trainees 87.0% -> 84.7% (fact sheet S42)
A3: MW02 | B3: HCLTech | C3: Q1 FY26 | D3: -161 | E3: -80 | F3: A | I3: =IF(AND(ISNUMBER(E3),ISNUMBER(H3),H3<>0),E3/H3,"") | J3: "Lower utilization due to specialized hiring and skill/location mismatch: 80 bps" | K3: Management, via broker note | L3: S25;S33 | M3: HCLTech does not publish utilisation, so bps per point cannot be computed
A4: MW03 | B4: Infosys | C4: Q2 FY21 | E4: 80 | F4: A | G4: 83.6 | H4: 2.4 | I4: =IF(AND(ISNUMBER(E4),ISNUMBER(H4),H4<>0),E4/H4,"") -> 33.333333 | J4: 80 bps of margin gain attributed to a 2.4% increase in utilisation (as recorded in D1) | K4: Infosys management | L4: S32;S72 | M4: Quarter confirmed: fact sheet S72 shows utilisation 81.2% → 83.6% (+2.4 pts) and margin 22.7% → 25.4%
A5: MW04 | B5: Infosys | C5: Q3 FY21 | E5: 100 | F5: B | G5: 86.3 | I5: =IF(AND(ISNUMBER(E5),ISNUMBER(H5),H5<>0),E5/H5,"") | J5: "a 100-basis points improvement due to better operating parameters like utilization, on-site mix and other cost levers" | K5: Nilanjan Roy (CFO) | L5: S17 | M5: Bundled: utilisation + onsite mix + other levers
A6: MW05 | B6: Infosys | C6: Q3 FY23 | D6: 0 | E6: -80 | F6: B | G6: 81.7 | H6: -1.9 | I6: =IF(AND(ISNUMBER(E6),ISNUMBER(H6),H6<>0),E6/H6,"") -> 42.105263 | J6: "80 basis points due to seasonal weakness in operating parameters, higher third-party costs, furloughs" | K6: Nilanjan Roy (CFO) | L6: S21 | M6: Bundled; utilisation fell to 81.7% excl. trainees
A7: MW06 | B7: Infosys | C7: Q2 FY24 | D7: 40 | E7: 50 | F7: B | G7: 81.8 | H7: 0.7 | I7: =IF(AND(ISNUMBER(E7),ISNUMBER(H7),H7<>0),E7/H7,"") -> 71.428571 | J7: "0.5% from cost optimization benefits" ... "comprising of higher utilization, pricing, etc." | K7: Nilanjan Roy (CFO) | L7: S22 | M7: Bundled: utilisation + pricing
A8: MW07 | B8: Wipro | C8: Q1 FY21 | D8: 140 | E8: 100 | F8: B | I8: =IF(AND(ISNUMBER(E8),ISNUMBER(H8),H8<>0),E8/H8,"") | J8: "the operation, which is nearly 1%" ... "you've seen utilization improving, you've seen offshore rate improving" | K8: Jatin Dalal (CFO) | L8: S24 | M8: Bundled; auto-generated transcript; components do not reconcile
A9: MW08 | B9: HCLTech | C9: Q2 FY24 | D9: 154 | F9: B | I9: =IF(AND(ISNUMBER(E9),ISNUMBER(H9),H9<>0),E9/H9,"") | J9: "EBIT margin improved 154 basis points sequentially to 18.5%, driven by productivity, utilization, and cost optimization" | K9: Call summary | L9: S27 | M9: Total only; no split by driver
A10: MW09 | B10: Infosys | C10: Q1 FY27 | F10: C | G10: 84.9 | H10: 1.9 | I10: =IF(AND(ISNUMBER(E10),ISNUMBER(H10),H10<>0),E10/H10,"") | J10: "utilization, excluding trainees, improving by 1.9% to 84.9%"; walk lists currency +70, Maximus +20, AI investment -50 bps | K10: Jayesh Sanghrajka (CFO) | L10: S14 | M10: Utilisation not given its own bps
A11: MW10 | B11: Infosys | C11: Q1 FY26 | D11: -20 | F11: C | G11: 85.2 | H11: 0.3 | I11: =IF(AND(ISNUMBER(E11),ISNUMBER(H11),H11<>0),E11/H11,"") | J11: "70 basis points from increase in realization due to Maximus and seasonality" | K11: Jayesh Sanghrajka (CFO) | L11: S20 | M11: Utilisation inside Project Maximus
A12: MW11 | B12: Infosys | C12: Q2 FY25 | D12: 0 | F12: C | G12: 85.9 | H12: 0.6 | I12: =IF(AND(ISNUMBER(E12),ISNUMBER(H12),H12<>0),E12/H12,"") | J12: "80 basis points benefit from Project Maximus" | K12: Jayesh Sanghrajka (CFO) | L12: S19 | M12: Utilisation inside Project Maximus
A13: MW12 | B13: Infosys | C13: Q3 FY25 | F13: C | G13: 86 | I13: =IF(AND(ISNUMBER(E13),ISNUMBER(H13),H13<>0),E13/H13,"") | J13: "30 bps from Project Maximus"; "86% is a little bit above our comfort level" | K13: Jayesh Sanghrajka (CFO) | L13: S18
A14: MW13 | B14: Infosys | C14: Q4 FY25 | F14: C | G14: 84.9 | I14: =IF(AND(ISNUMBER(E14),ISNUMBER(H14),H14<>0),E14/H14,"") | J14: "30 basis points from Maximus"; compensation -140 bps | K14: Jayesh Sanghrajka (CFO) | L14: S15
A15: MW14 | B15: TCS | C15: Q4 FY25 | D15: -30 | F15: C | I15: =IF(AND(ISNUMBER(E15),ISNUMBER(H15),H15<>0),E15/H15,"") | J15: "we focused on improving utilization, productivity and realization" (not quantified) | K15: Samir Seksaria (CFO) | L15: S23 | M15: Named drivers net -120 bps vs reported -30 bps
A16: MW15 | B16: Tech Mahindra | C16: Q1 FY26 | D16: 60 | F16: C | I16: =IF(AND(ISNUMBER(E16),ISNUMBER(H16),H16<>0),E16/H16,"") | J16: "Headwinds on margin came from ... lower utilization" (not quantified) | K16: Broker note | L16: S28 | M16: Utilisation incl. trainees 85.1%
A17: MW16 | B17: HCLTech | C17: FY26 guidance | F17: C | I17: =IF(AND(ISNUMBER(E17),ISNUMBER(H17),H17<>0),E17/H17,"") | J17: "lower Utilization ... to cost 10-20 bps" (forward-looking guidance) | K17: Management, via broker note | L17: S25 | M17: Guidance, not an outcome; exclude from estimation
A18: MW17 | B18: Infosys | C18: Q1 FY20 | D18: -100 | E18: 70 | F18: A | G18: 83.1 | H18: 0.8 | I18: =IF(AND(ISNUMBER(E18),ISNUMBER(H18),H18<>0),E18/H18,"") -> 87.5 | J18: "increases in utilization, which helped margins by 70 basis points" | K18: Nilanjan Roy (CFO) | L18: S74;S73 | M18: Utilisation 82.3% (S73) → 83.1%; CFO said 'up nearly 70 basis points'
A19: MW18 | B19: Infosys | C19: Q2 FY19 (year-on-year) | E19: 40 | F19: A | G19: 85.6 | I19: =IF(AND(ISNUMBER(E19),ISNUMBER(H19),H19<>0),E19/H19,"") | J19: "higher utilization of 40 basis points" (year-on-year reconciliation) | K19: M.D. Ranganath (CFO) | L19: S77 | M19: Year-on-year, not sequential; Q2 FY18 utilisation needed to compute bps per point
A20: MW19 | B20: Infosys | C20: Q3 FY19 | D20: -110 | E20: -80 | F20: B | G20: 83.8 | H20: -1.8 | I20: =IF(AND(ISNUMBER(E20),ISNUMBER(H20),H20<>0),E20/H20,"") -> 44.444444 | J20: "drop in utilization and higher onsite mix impacted operating margin by 80 basis points" | K20: Jayesh Sanghrajka (CFO) | L20: S78 | M20: Bundled with onsite mix; utilisation 85.6% → 83.8% (furloughs)
A21: MW20 | B21: Infosys | C21: Q4 FY18 | D21: 40 | F21: B | G21: 84.7 | I21: =IF(AND(ISNUMBER(E21),ISNUMBER(H21),H21<>0),E21/H21,"") | J21: "Currency movement helped the margins by 20 basis points which was fully offset by drop in utilization and price realization" | K21: M.D. Ranganath (CFO) | L21: S76 | M21: Utilisation + pricing about −20 bps combined; not separable
A22: MW21 | B22: Infosys | C22: Q2 FY20 | D22: 120 | E22: 110 | F22: B | G22: 84.9 | H22: 1.8 | I22: =IF(AND(ISNUMBER(E22),ISNUMBER(H22),H22<>0),E22/H22,"") -> 61.111111 | J22: "Higher utilization, lower onsite mix and other cost optimization measures helped operating margins by 110 basis points" | K22: Nilanjan Roy (CFO) | L22: S79 | M22: Bundled; utilisation +1.8 pts per COO
A23: MW22 | B23: Tech Mahindra | C23: Q3 FY19 | D23: 50 | E23: 40 | F23: A | I23: =IF(AND(ISNUMBER(E23),ISNUMBER(H23),H23<>0),E23/H23,"") | J23: "also about utilization which was helping to the tune of about 40 basis" | K23: Manoj Bhat (CFO) | L23: S80 | M23: Utilisation change not stated; needs TechM Q2–Q3 FY19 fact sheets
A24: MW23 | B24: Tech Mahindra | C24: Q3 FY16 | D24: 30 | F24: C | I24: =IF(AND(ISNUMBER(E24),ISNUMBER(H24),H24<>0),E24/H24,"") | J24: "The margin tailwinds came from cost optimization program, improved utilization, lower SG&A" | K24: Milind Kulkarni (CFO) | L24: S83 | M24: EBITDA margin basis
A25: MW24 | B25: TCS | C25: Q2 FY26 | D25: 70 | F25: C | I25: =IF(AND(ISNUMBER(E25),ISNUMBER(H25),H25<>0),E25/H25,"") | J25: Currency +80, wage hike and QVA −70, pyramid rebalancing +40, operating efficiency +20 bps; excl. one-time severance | K25: Samir Seksaria (CFO) | L25: S84 | M25: First full quarter after the 35-day bench cap; utilisation not named
A26: MW25 | B26: TCS | C26: Q1 FY27 | D26: -130 | F26: C | I26: =IF(AND(ISNUMBER(E26),ISNUMBER(H26),H26<>0),E26/H26,"") | J26: "annual increments ... impacted margins by 170 bps"; currency and efficiency +40 bps | K26: Samir Seksaria (CFO) | L26: S85 | M26: Wage-hike quarter
A27: MW26 | B27: TCS | C27: Q2 FY27 | D27: 0 | F27: C | I27: =IF(AND(ISNUMBER(E27),ISNUMBER(H27),H27<>0),E27/H27,"") | J27: "we have invested in a higher bench and increased hiring of subcontractors"; utilisation named as a lever | K27: Samir Seksaria (CFO) | L27: S86 | M27: Bench rebuilt after the 2025 policy
A28: MW27 | B28: TCS | C28: Q3 FY26 | D28: 0 | F28: C | I28: =IF(AND(ISNUMBER(E28),ISNUMBER(H28),H28<>0),E28/H28,"") | J28: Productivity, pyramid and efficiencies +80, currency +20, full-quarter wage impact −50, brand and partnerships −50 bps | K28: Samir Seksaria (CFO) | L28: S106 | M28: Margin stable at 25.2%; utilisation not named
A29: MW28 | B29: TCS | C29: Q1 FY26 | D29: 30 | F29: C | I29: =IF(AND(ISNUMBER(E29),ISNUMBER(H29),H29<>0),E29/H29,"") | J29: "The demand contraction during the quarter had an impact on our utilization"; offset by lower third-party costs and currency | K29: Samir Seksaria (CFO) | L29: S105 | M29: Policy quarter (cap from 12 Jun 2025); utilisation fell, not quantified
A30: MW29 | B30: TCS | C30: Q4 FY26 | D30: 10 | F30: C | I30: =IF(AND(ISNUMBER(E30),ISNUMBER(H30),H30<>0),E30/H30,"") | J30: Realisations +40, currency +110, external consultants and build −40, partner and go-to-market −50, integration −10 bps | K30: Samir Seksaria (CFO) | L30: S107 | M30: Utilisation and bench not discussed

Sheet Policy_Events
A1: event_id | B1: firm | C1: policy / event | D1: effective_date | E1: first_affected_quarter | F1: source_id | G1: analysis_use | H1: verification
A2: PE01 | B2: TCS | C2: Bench cap: 35 business days a year; 225 billable days rule | D2: 2025-06-12 | E2: Q1 FY26 (effective mid-quarter) | F2: S35;S40 | G2: Pre-period Q2 FY25–Q1 FY26 vs post Q2 FY26 onward; TCS later rebuilt bench (S36) | H2: Second source: S40 teaching case
A3: PE02 | B3: Wipro | C3: Bench window up to 180 days for Band 2 and below; 45 days for Band 3 and above | D3: 2026-10-01 | E3: Q3 FY27 (first full quarter) | F3: S34 | G3: First post-policy result: Q3 FY27, due ~Jan 2027 | H3: Single news source; seek company confirmation
A4: PE03 | B4: TCS | C4: CFO says TCS invested in a higher bench and more subcontractors | D4: 2026-10 (Q2 FY27 call) | E4: Q2 FY27 | F4: S36 | G4: Counter-evidence: policy did not keep bench low | H4: From D1
A5: PE04 | B5: TCS | C5: NITES union complaint to Ministry of Labour and Employment | D5: 2025-07 | E5: Q2 FY26 | F5: S39 | G5: Labour-relations risk context | H5: From D1

Sheet Coverage_Check
A1: Week-1 coverage check vs D1 success metrics (all figures are live formulas on Quarterly_Panel and Margin_Walks)
A3: firm | B3: firm-quarters in panel | C3: with op margin | D3: with utilisation (excl. trainees) | E3: % with utilisation | F3: first quarter | G3: last quarter
A4: Wipro | B4: =COUNTIF(Quarterly_Panel!$A$2:$A$135,A4) -> 50 | C4: =COUNTIFS(Quarterly_Panel!$A$2:$A$135,A4,Quarterly_Panel!$D$2:$D$135,"<>") -> 50 | D4: =COUNTIFS(Quarterly_Panel!$A$2:$A$135,A4,Quarterly_Panel!$F$2:$F$135,"<>") -> 50 | E4: =IF(B4=0,"",D4/B4) -> 1 | F4: =INDEX(Quarterly_Panel!$B$2:$B$135,MATCH(A4,Quarterly_Panel!$A$2:$A$135,0)) -> Q1 FY15 | G4: =INDEX(Quarterly_Panel!$B$2:$B$135,MATCH(A4,Quarterly_Panel!$A$2:$A$135,0)+B4-1) -> Q2 FY27
A5: Infosys | B5: =COUNTIF(Quarterly_Panel!$A$2:$A$135,A5) -> 30 | C5: =COUNTIFS(Quarterly_Panel!$A$2:$A$135,A5,Quarterly_Panel!$D$2:$D$135,"<>") -> 30 | D5: =COUNTIFS(Quarterly_Panel!$A$2:$A$135,A5,Quarterly_Panel!$F$2:$F$135,"<>") -> 30 | E5: =IF(B5=0,"",D5/B5) -> 1 | F5: =INDEX(Quarterly_Panel!$B$2:$B$135,MATCH(A5,Quarterly_Panel!$A$2:$A$135,0)) -> Q4 FY19 | G5: =INDEX(Quarterly_Panel!$B$2:$B$135,MATCH(A5,Quarterly_Panel!$A$2:$A$135,0)+B5-1) -> Q1 FY27
A6: TCS | B6: =COUNTIF(Quarterly_Panel!$A$2:$A$135,A6) -> 19 | C6: =COUNTIFS(Quarterly_Panel!$A$2:$A$135,A6,Quarterly_Panel!$D$2:$D$135,"<>") -> 19 | D6: =COUNTIFS(Quarterly_Panel!$A$2:$A$135,A6,Quarterly_Panel!$F$2:$F$135,"<>") -> 0 | E6: =IF(B6=0,"",D6/B6) -> 0 | F6: =INDEX(Quarterly_Panel!$B$2:$B$135,MATCH(A6,Quarterly_Panel!$A$2:$A$135,0)) -> Q4 FY22 | G6: =INDEX(Quarterly_Panel!$B$2:$B$135,MATCH(A6,Quarterly_Panel!$A$2:$A$135,0)+B6-1) -> Q2 FY27
A7: HCLTech | B7: =COUNTIF(Quarterly_Panel!$A$2:$A$135,A7) -> 9 | C7: =COUNTIFS(Quarterly_Panel!$A$2:$A$135,A7,Quarterly_Panel!$D$2:$D$135,"<>") -> 9 | D7: =COUNTIFS(Quarterly_Panel!$A$2:$A$135,A7,Quarterly_Panel!$F$2:$F$135,"<>") -> 0 | E7: =IF(B7=0,"",D7/B7) -> 0 | F7: =INDEX(Quarterly_Panel!$B$2:$B$135,MATCH(A7,Quarterly_Panel!$A$2:$A$135,0)) -> Q2 FY25 | G7: =INDEX(Quarterly_Panel!$B$2:$B$135,MATCH(A7,Quarterly_Panel!$A$2:$A$135,0)+B7-1) -> Q2 FY27
A8: LTIMindtree | B8: =COUNTIF(Quarterly_Panel!$A$2:$A$135,A8) -> 15 | C8: =COUNTIFS(Quarterly_Panel!$A$2:$A$135,A8,Quarterly_Panel!$D$2:$D$135,"<>") -> 15 | D8: =COUNTIFS(Quarterly_Panel!$A$2:$A$135,A8,Quarterly_Panel!$F$2:$F$135,"<>") -> 13 | E8: =IF(B8=0,"",D8/B8) -> 0.86666667 | F8: =INDEX(Quarterly_Panel!$B$2:$B$135,MATCH(A8,Quarterly_Panel!$A$2:$A$135,0)) -> Q2 FY23 | G8: =INDEX(Quarterly_Panel!$B$2:$B$135,MATCH(A8,Quarterly_Panel!$A$2:$A$135,0)+B8-1) -> Q1 FY27
A9: Tech Mahindra | B9: =COUNTIF(Quarterly_Panel!$A$2:$A$135,A9) -> 11 | C9: =COUNTIFS(Quarterly_Panel!$A$2:$A$135,A9,Quarterly_Panel!$D$2:$D$135,"<>") -> 11 | D9: =COUNTIFS(Quarterly_Panel!$A$2:$A$135,A9,Quarterly_Panel!$F$2:$F$135,"<>") -> 10 | E9: =IF(B9=0,"",D9/B9) -> 0.90909091 | F9: =INDEX(Quarterly_Panel!$B$2:$B$135,MATCH(A9,Quarterly_Panel!$A$2:$A$135,0)) -> Q4 FY24 | G9: =INDEX(Quarterly_Panel!$B$2:$B$135,MATCH(A9,Quarterly_Panel!$A$2:$A$135,0)+B9-1) -> Q2 FY27
A10: Total | B10: =SUM(B4:B9) -> 134 | C10: =SUM(C4:C9) -> 134 | D10: =SUM(D4:D9) -> 103 | E10: =IF(B10=0,"",D10/B10) -> 0.76865672
A12: D1 metric | B12: Target | C12: Actual (formula) | D12: Status
A13: Margin-walk statements, Tier A (utilisation isolated, bps) | B13: 15 firm-quarters | C13: =COUNTIF(Margin_Walks!$F$2:$F$30,"A") -> 6 | D13: =IF(C13>=15,"Met","Not met") -> Not met
A14: Firms with ≥1 Tier A statement | B14: 4 firms | C14: =SUMPRODUCT((Margin_Walks!$F$2:$F$30="A")/COUNTIFS(Margin_Walks!$B$2:$B$30,Margin_Walks!$B$2:$B$30,Margin_Walks!$F$2:$F$30,Margin_Walks!$F$2:$F$30)) -> 3 | D14: =IF(C14>=4,"Met","Not met") -> Not met
A15: Tier A + B statements (utilisation named with a bps figure) | B15: (context) | C15: =COUNTIF(Margin_Walks!$F$2:$F$30,"A")+COUNTIF(Margin_Walks!$F$2:$F$30,"B") -> 14 | D15: Info
A16: Statements where bps per utilisation point is computable (Tier A or B, utilisation change known) | B16: (context) | C16: =COUNT(Margin_Walks!$I$2:$I$30) -> 7 | D16: Info
A17: Firm-quarters with utilisation (excl. trainees), firms that report it: Wipro, Infosys, LTIMindtree | B17: ≥90% | C17: =(D4+D5+D8)/(B4+B5+B8) -> 0.97894737 | D17: =IF(C17>=0.9,"Met","Not met") -> Met
A18: Panel rows traceable to a Source_Log id | B18: 100% | C18: =COUNTIF(Quarterly_Panel!$L$2:$L$135,"S*")/COUNTA(Quarterly_Panel!$A$2:$A$135) -> 1 | D18: =IF(C18=1,"Met","Not met") -> Met
A19: Wipro quarters in panel (D1 plan: ~40) | B19: ~40 | C19: =B4 -> 50 | D19: =IF(C19>=40,"Met","Partial — back-fill FY15–FY19 from datasheets (S09)") -> Met

Sheet Data_Quality_Log
A1: issue_id | B1: severity | C1: area | D1: finding | E1: affects | F1: action | G1: owner | H1: status
A2: DQ01 | B2: Critical | C2: Bloomberg exports | D2: 25 of 26 files hold unevaluated BDH/BQL formulas; 282 of 12,460 requested cells (2.3%) have values. KPIC_IT_Services (peer utilisation, attrition, margin) has 0 values. | E2: All Bloomberg-based panels | F2: v1.1: Bloomberg no longer needed for the panel — peers rebuilt from company fact sheets/filings. Optional later: refresh on terminal and use as a third source | G2: James | H2: Mitigated (v1.1)
A3: DQ02 | B3: High | C3: Bloomberg KPIC window | D3: KPIC requests only 8 quarters (CY2025Q2–CY2027Q1 = Q1 FY26–Q4 FY27), of which 2 are estimates. | E3: Peer panel depth | F3: Superseded by fact-sheet panel (v1.1) | G3: James | H3: Closed
A4: DQ03 | B4: High | C4: TCS / HCLTech disclosure | D4: TCS and HCLTech do not publish utilisation in fact sheets/releases. | E4: TCS before/after test; regression sample | F4: Confirmed again in v1.1 across 6 TCS fact sheets and 4 HCLTech releases: utilisation never disclosed. TCS before/after runs on margin + headcount (19 quarters, Q4 FY22–Q2 FY27) and states that utilisation is unobserved | G4: Abhiroop | H4: Open — guide decision
A5: DQ04 | B5: High | C5: Margin-walk coverage | D5: v1.2: 6 Tier A statements across 3 firms (Infosys 4, HCLTech 1, Tech Mahindra 1) after searching FY18–FY27 calls, vs D1 target of 15 across 4. Infosys bundles utilisation into 'Project Maximus' from FY21; TCS names utilisation without sizing it. | E5: D4 primary estimate | F5: Extend transcript search to FY15–FY20 (pre-Maximus) in sprint 2; propose to guide that the regression becomes the primary estimate and walks the bounding check | G5: James / Abhiroop | H5: Open — guide decision
A6: DQ05 | B6: Medium | C6: Margin basis | D6: Wipro = IT Services segment margin; Infosys/TCS = company; HCLTech = company EBIT incl. restructuring; LTIM/TechM = company EBIT. | E6: Cross-firm comparison | F6: Compare QoQ bps changes, not levels; margin_basis column carried on every row | G6: James | H6: Mitigated
A7: DQ06 | B7: Medium | C7: Utilisation definition | D7: Excl. trainees (Wipro, Infosys) vs incl. trainees (Tech Mahindra, Infosys secondary) vs gross (Wipro to FY22). | E7: Pooled regression | F7: Separate columns; pooled models use excl-trainee series only | G7: James | H7: Mitigated
A8: DQ07 | B8: Medium | C8: Infosys Q4 FY26 | D8: Fact sheet shows 20.9% (USD table) and 21.0% (INR table). | E8: 1 row | F8: Panel uses 20.9% (USD table, consistent with other rows); logged | G8: James | H8: Closed
A9: DQ08 | B9: Medium | C9: One-off items | D9: Wipro Q2 FY26 customer-bankruptcy provision (16.7% reported, 17.2% excl.); HCLTech restructuring 55/62/84 bps. | E9: Regression residuals | F9: Flag in note column; D4 adds one-off dummies | G9: Abhiroop | H9: Open
A10: DQ09 | B10: Low | C10: PDF extraction | D10: Wipro datasheet column headers are garbled in PDF text; quarter mapping anchored on revenue figures and overlap between datasheets. | E10: Wipro panel | F10: Overlaps agree (Q2 FY24 in S04 and S05; Q1 FY26–Q1 FY27 vs D1). Manual 10% spot-check against PDFs before D3 | G10: James | H10: Partly verified
A11: DQ10 | B11: Medium | C11: Restatements | D11: Found in v1.2: Wipro Q4 FY16 (20.1% → 19.7%, headcount 172,912 → 156,831) and Q4 FY18 (14.4% → 14.6%, revenue 2,062.0 → 2,019.1) restated in the next year's datasheet. FY23 values still taken from the FY24 sheet. | E11: Wipro panel | F11: Panel keeps originally reported values from each year's own Q4 datasheet; restated values in note column. Wipro headcount definition breaks between FY16 and FY17 — do not use headcount levels across that break | G11: James | H11: Logged
A12: DQ11 | B12: Low | C12: Infosys gaps and bases | D12: v1.2: Infosys Q4 FY19–Q1 FY27 complete from fact sheets except Q1 FY20 (transcript). Attrition before FY22 is 'annualised', not LTM — not comparable with later values. Q2 FY27 not published at build date. | E12: Infosys panel | F12: Do not use pre-FY22 attrition in pooled models; add Q2 FY27 when released | G12: James | H12: Mostly closed
... A20: DQ15 | B20: Info | C20: Privacy | D20: No employee, client or personal data collected. Named people are public company officers quoted from public calls. | E20: All | F20: Datasheet section 'Privacy and consent' | G20: James | H20: Closed

Sheet Bloomberg_File_Audit
A1: file | B1: bloomberg_page | C1: cells_requested | D1: values_cached | E1: not_cached | F1: pct_populated | G1: estimate_cells | H1: n_periods | I1: relevance
A2: FA_5fdp10z5.xlsx | B2: Wipro Ltd (WPRO IN) - Credit | C2: 324 | D2: 0 | E2: =C2-D2 -> 324 | F2: =IF(C2=0,"",D2/C2) -> 0 | G2: 0 | H2: 12 | I2: Low / out of scope
A3: FA_5x1gxcp1.xlsx | B3: Wipro Ltd (WPRO IN) - Working Capital | C3: 91 | D3: 0 | E3: =C3-D3 -> 91 | F3: =IF(C3=0,"",D3/C3) -> 0 | G3: 0 | H3: 7 | I3: Low / out of scope
A4: FA_WPRO_IN.xlsx | B4: WPRO IN Equity | C4: 1287 | D4: 0 | E4: =C4-D4 -> 1287 | F4: =IF(C4=0,"",D4/C4) -> 0 | G4: 286 | H4: 9 | I4: High — Wipro segment financials
A5: FA_azncqfkn.xlsx | B5: Wipro Ltd (WPRO IN) - Standardized | C5: 599 | D5: 49 | E5: =C5-D5 -> 550 | F5: =IF(C5=0,"",D5/C5) -> 0.081803005 | G5: 0 | H5: 12 | I5: Low — cash flow
A6: FA_dmwyxgqw.xlsx | B6: Wipro Ltd (WPRO IN) - Standardized | C6: 1080 | D6: 0 | E6: =C6-D6 -> 1080 | F6: =IF(C6=0,"",D6/C6) -> 0 | G6: 0 | H6: 12 | I6: Low / out of scope
A7: FA_dn2dasbg.xlsx | B7: Wipro Ltd (WPRO IN) - BBG Adjusted | C7: 742 | D7: 103 | E7: =C7-D7 -> 639 | F7: =IF(C7=0,"",D7/C7) -> 0.13881402 | G7: 44 | H7: 12 | I7: High — Wipro P&L, personnel expense
A8: FA_dqo4tbkk.xlsx | B8: Wipro Ltd (WPRO IN) - Overview | C8: 230 | D8: 48 | E8: =C8-D8 -> 182 | F8: =IF(C8=0,"",D8/C8) -> 0.20869565 | G8: 24 | H8: 10 | I8: Medium — overview
A9: FA_go4iyotq.xlsx | B9: Wipro Ltd (WPRO IN) - Social | C9: 430 | D9: 0 | E9: =C9-D9 -> 430 | F9: =IF(C9=0,"",D9/C9) -> 0 | G9: 0 | H9: 10 | I9: Low / out of scope
A10: FA_hxqp1f2p.xlsx | B10: Wipro Ltd (WPRO IN) - Profitability | C10: 180 | D10: 0 | E10: =C10-D10 -> 180 | F10: =IF(C10=0,"",D10/C10) -> 0 | G10: 0 | H10: 12 | I10: Medium — profitability ratios
A11: FA_jces214e.xlsx | B11: Wipro Ltd (WPRO IN) - Dividend Summary | C11: 92 | D11: 4 | E11: =C11-D11 -> 88 | F11: =IF(C11=0,"",D11/C11) -> 0.043478261 | G11: 4 | H11: 10 | I11: Low / out of scope
A12: FA_jgsobeh5.xlsx | B12: Wipro Ltd (WPRO IN) - Contractual Obligations | C12: 130 | D12: 0 | E12: =C12-D12 -> 130 | F12: =IF(C12=0,"",D12/C12) -> 0 | G12: 0 | H12: 10 | I12: Low / out of scope
A13: FA_lspst4u3.xlsx | B13: Wipro Ltd (WPRO IN) - As Reported Summary | C13: 150 | D13: 0 | E13: =C13-D13 -> 150 | F13: =IF(C13=0,"",D13/C13) -> 0 | G13: 0 | H13: 10 | I13: Medium — as reported
... A27: KPIC_IT_Services.xlsx | B27: IT Services | C27: 3480 | D27: 0 | E27: =C27-D27 -> 3480 | F27: =IF(C27=0,"",D27/C27) -> 0 | G27: 870 | H27: 8 | I27: High — peer quarterly utilisation, attrition, margin
A28: Total | C28: =SUM(C2:C27) -> 12460 | D28: =SUM(D2:D27) -> 282 | E28: =SUM(E2:E27) -> 12178 | F28: =D28/C28 -> 0.022632424 | G28: =SUM(G2:G27) -> 1258

Sheet Bloomberg_Values
A1: Values cached in the Bloomberg exports (S01). 'Last 12M' / TTM = 12 months to 30-Sep-2026. is_estimate=1 rows are Bloomberg consensus (BEst) and are NOT actuals. Duplicate rows across pages removed.
A3: file | B3: page | C3: section | D3: row_label | E3: mnemonic | F3: period | G3: period_end | H3: is_estimate | I3: value
A4: FA_azncqfkn.xlsx | B4: Wipro Ltd (WPRO IN) - Standardized | C4: Cash from Operating Activities | D4: + Net Income | E4: CF_NET_INC | F4: Last 12M | G4: 09/30/2026 | H4: 0 | I4: 131734
A5: FA_azncqfkn.xlsx | B5: Wipro Ltd (WPRO IN) - Standardized | C5: Cash from Operating Activities | D5: + Depreciation & Amortization | E5: CF_DEPR_AMORT | F5: Last 12M | G5: 09/30/2026 | H5: 0 | I5: 32146
A6: FA_azncqfkn.xlsx | B6: Wipro Ltd (WPRO IN) - Standardized | C6: Cash from Operating Activities | D6: + Non-Cash Items | E6: NON_CASH_ITEMS_DETAILED | F6: Last 12M | G6: 09/30/2026 | H6: 0 | I6: 27101
A7: FA_azncqfkn.xlsx | B7: Wipro Ltd (WPRO IN) - Standardized | C7: Cash from Operating Activities | D7: + Stock-Based Compensation | E7: CF_STOCK_BASED_COMPENSATION | F7: Last 12M | G7: 09/30/2026 | H7: 0 | I7: 4711
A8: FA_azncqfkn.xlsx | B8: Wipro Ltd (WPRO IN) - Standardized | C8: Cash from Operating Activities | D8: + Other Non-Cash Adj | E8: OTHER_NON_CASH_ADJ_LESS_DETAILED | F8: Last 12M | G8: 09/30/2026 | H8: 0 | I8: 22390
A9: FA_azncqfkn.xlsx | B9: Wipro Ltd (WPRO IN) - Standardized | C9: Cash from Operating Activities | D9: + Chg in Non-Cash Work Cap | E9: CF_CHNG_NON_CASH_WORK_CAP | F9: Last 12M | G9: 09/30/2026 | H9: 0 | I9: -8441
A10: FA_azncqfkn.xlsx | B10: Wipro Ltd (WPRO IN) - Standardized | C10: Cash from Operating Activities | D10: + (Inc) Dec in Accts Receiv | E10: CF_ACCT_RCV_UNBILLED_REV | F10: Last 12M | G10: 09/30/2026 | H10: 0 | I10: -2168
A11: FA_azncqfkn.xlsx | B11: Wipro Ltd (WPRO IN) - Standardized | C11: Cash from Operating Activities | D11: + (Inc) Dec in Inventories | E11: CF_CHANGE_IN_INVENTORIES | F11: Last 12M | G11: 09/30/2026 | H11: 0 | I11: -96
A12: FA_azncqfkn.xlsx | B12: Wipro Ltd (WPRO IN) - Standardized | C12: Cash from Operating Activities | D12: + Inc (Dec) in Other | E12: INC_DEC_IN_OT_OP_AST_LIAB_DETAIL | F12: Last 12M | G12: 09/30/2026 | H12: 0 | I12: -6177
A13: FA_azncqfkn.xlsx | B13: Wipro Ltd (WPRO IN) - Standardized | C13: Cash from Operating Activities | D13: + Net Cash From Disc Ops | E13: CF_NET_CASH_DISCONT_OPS_OPER | F13: Last 12M | G13: 09/30/2026 | H13: 0 | I13: 0
A14: FA_azncqfkn.xlsx | B14: Wipro Ltd (WPRO IN) - Standardized | C14: Cash from Operating Activities | D14: Cash from Operating Activities | E14: CF_CASH_FROM_OPER | F14: Last 12M | G14: 09/30/2026 | H14: 0 | I14: 182540
A15: FA_azncqfkn.xlsx | B15: Wipro Ltd (WPRO IN) - Standardized | C15: Cash from Investing Activities | D15: + Change in Fixed & Intang | E15: FIXED_INTANG_ASST_CHANGE | F15: Last 12M | G15: 09/30/2026 | H15: 0 | I15: -16840
... A50: FA_azncqfkn.xlsx | B50: Wipro Ltd (WPRO IN) - Standardized | C50: Reference Items | D50: Cash Flow to Net Income | E50: CASH_FLOW_TO_NET_INC | F50: Last 12M | G50: 09/30/2026 | H50: 0 | I50: 1.7951322
A51: FA_dn2dasbg.xlsx | B51: Wipro Ltd (WPRO IN) - BBG Adjusted | D51: Revenue | E51: SALES_REV_TURN | F51: Last 12M | G51: 09/30/2026 | H51: 0 | I51: 970234
A52: FA_dn2dasbg.xlsx | B52: Wipro Ltd (WPRO IN) - BBG Adjusted | D52: Revenue | E52: SALES_REV_TURN | F52: FY 2027 Est | G52: 03/31/2027 | H52: 1 | I52: 989878.6
A53: FA_dn2dasbg.xlsx | B53: Wipro Ltd (WPRO IN) - BBG Adjusted | D53: Revenue | E53: SALES_REV_TURN | F53: FY 2028 Est | G53: 03/31/2028 | H53: 1 | I53: 1017536.7
A54: FA_dn2dasbg.xlsx | B54: Wipro Ltd (WPRO IN) - BBG Adjusted | D54: + Sales & Services Revenue | E54: IS_SALES_AND_SERVICES_REVENUES | F54: Last 12M | G54: 09/30/2026 | H54: 0 | I54: 970234
A55: FA_dn2dasbg.xlsx | B55: Wipro Ltd (WPRO IN) - BBG Adjusted | D55: - Cost of Revenue | E55: IS_COGS_TO_FE_AND_PP_AND_G | F55: Last 12M | G55: 09/30/2026 | H55: 0 | I55: 690084
A56: FA_dn2dasbg.xlsx | B56: Wipro Ltd (WPRO IN) - BBG Adjusted | D56: + Cost of Goods & Services | E56: IS_COG_AND_SERVICES_SOLD | F56: Last 12M | G56: 09/30/2026 | H56: 0 | I56: 690084
A57: FA_dn2dasbg.xlsx | B57: Wipro Ltd (WPRO IN) - BBG Adjusted | D57: Gross Profit | E57: GROSS_PROFIT | F57: Last 12M | G57: 09/30/2026 | H57: 0 | I57: 280150
A58: FA_dn2dasbg.xlsx | B58: Wipro Ltd (WPRO IN) - BBG Adjusted | D58: Gross Profit | E58: GROSS_PROFIT | F58: FY 2027 Est | G58: 03/31/2027 | H58: 1 | I58: 290697.65
A59: FA_dn2dasbg.xlsx | B59: Wipro Ltd (WPRO IN) - BBG Adjusted | D59: Gross Profit | E59: GROSS_PROFIT | F59: FY 2028 Est | G59: 03/31/2028 | H59: 1 | I59: 306532.94
A60: FA_dn2dasbg.xlsx | B60: Wipro Ltd (WPRO IN) - BBG Adjusted | D60: + Other Operating Income | E60: IS_OTHER_OPER_INC | F60: Last 12M | G60: 09/30/2026 | H60: 0 | I60: 0
A61: FA_dn2dasbg.xlsx | B61: Wipro Ltd (WPRO IN) - BBG Adjusted | D61: - Operating Expenses | E61: IS_OPERATING_EXPN | F61: Last 12M | G61: 09/30/2026 | H61: 0 | I61: 119054
A62: FA_dn2dasbg.xlsx | B62: Wipro Ltd (WPRO IN) - BBG Adjusted | D62: + Selling, General & Admin | E62: IS_SGA_EXPENSE | F62: Last 12M | G62: 09/30/2026 | H62: 0 | I62: 125148
... A129: FA_dn2dasbg.xlsx | B129: Wipro Ltd (WPRO IN) - BBG Adjusted | D129: Diluted EPS from Cont Ops, Adjusted | E129: IS_DIL_EPS_CONT_OPS | F129: FY 2028 Est | G129: 03/31/2028 | H129: 1 | I129: 13.733
A130: FA_dn2dasbg.xlsx | B130: Wipro Ltd (WPRO IN) - BBG Adjusted | C130: Reference Items | D130: EBITDA | E130: EBITDA | F130: Last 12M | G130: 09/30/2026 | H130: 0 | I130: 193242
A131: FA_dn2dasbg.xlsx | B131: Wipro Ltd (WPRO IN) - BBG Adjusted | C131: Reference Items | D131: EBITDA | E131: EBITDA | F131: FY 2027 Est | G131: 03/31/2027 | H131: 1 | I131: 194071.61
A132: FA_dn2dasbg.xlsx | B132: Wipro Ltd (WPRO IN) - BBG Adjusted | C132: Reference Items | D132: EBITDA | E132: EBITDA | F132: FY 2028 Est | G132: 03/31/2028 | H132: 1 | I132: 200107.31
A133: FA_dn2dasbg.xlsx | B133: Wipro Ltd (WPRO IN) - BBG Adjusted | C133: Reference Items | D133: EBITDA Margin (T12M) | E133: EBITDA_MARGIN | F133: Last 12M | G133: 09/30/2026 | H133: 0 | I133: 19.917051
A134: FA_dn2dasbg.xlsx | B134: Wipro Ltd (WPRO IN) - BBG Adjusted | C134: Reference Items | D134: EBITDA Margin (T12M) | E134: EBITDA_MARGIN | F134: FY 2027 Est | G134: 03/31/2027 | H134: 1 | I134: 19.605597
A135: FA_dn2dasbg.xlsx | B135: Wipro Ltd (WPRO IN) - BBG Adjusted | C135: Reference Items | D135: EBITDA Margin (T12M) | E135: EBITDA_MARGIN | F135: FY 2028 Est | G135: 03/31/2028 | H135: 1 | I135: 19.665856
A136: FA_dn2dasbg.xlsx | B136: Wipro Ltd (WPRO IN) - BBG Adjusted | C136: Reference Items | D136: EBITA | E136: EBITA | F136: Last 12M | G136: 09/30/2026 | H136: 0 | I136: 170835
A137: FA_dn2dasbg.xlsx | B137: Wipro Ltd (WPRO IN) - BBG Adjusted | C137: Reference Items | D137: EBIT | E137: EBIT | F137: Last 12M | G137: 09/30/2026 | H137: 0 | I137: 161096
A138: FA_dn2dasbg.xlsx | B138: Wipro Ltd (WPRO IN) - BBG Adjusted | C138: Reference Items | D138: EBIT | E138: EBIT | F138: FY 2027 Est | G138: 03/31/2027 | H138: 1 | I138: 161464.79
A139: FA_dn2dasbg.xlsx | B139: Wipro Ltd (WPRO IN) - BBG Adjusted | C139: Reference Items | D139: EBIT | E139: EBIT | F139: FY 2028 Est | G139: 03/31/2028 | H139: 1 | I139: 167960.38
A140: FA_dn2dasbg.xlsx | B140: Wipro Ltd (WPRO IN) - BBG Adjusted | C140: Reference Items | D140: Gross Margin | E140: GROSS_MARGIN | F140: Last 12M | G140: 09/30/2026 | H140: 0 | I140: 28.874478
A141: FA_dn2dasbg.xlsx | B141: Wipro Ltd (WPRO IN) - BBG Adjusted | C141: Reference Items | D141: Gross Margin | E141: GROSS_MARGIN | F141: FY 2027 Est | G141: 03/31/2027 | H141: 1 | I141: 29.367
... A153: FA_dn2dasbg.xlsx | B153: Wipro Ltd (WPRO IN) - BBG Adjusted | C153: Reference Items | D153: Depreciation Expense | E153: IS_DEPR_EXP | F153: Last 12M | G153: 09/30/2026 | H153: 0 | I153: 22407
A154: FA_dqo4tbkk.xlsx | B154: Wipro Ltd (WPRO IN) - Overview | D154: Number of Employees | E154: NUM_OF_EMPLOYEES | F154: Last 12M | G154: 09/30/2026 | H154: 0 | I154: 236328
A155: FA_dqo4tbkk.xlsx | B155: Wipro Ltd (WPRO IN) - Overview | D155: Last Price | E155: PX_LAST | F155: Last 12M | G155: 09/30/2026 | H155: 0 | I155: 184
A156: FA_dqo4tbkk.xlsx | B156: Wipro Ltd (WPRO IN) - Overview | D156: Shares Outstanding | E156: BS_SH_OUT | F156: Last 12M | G156: 09/30/2026 | H156: 0 | I156: 9905.2457
A157: FA_dqo4tbkk.xlsx | B157: Wipro Ltd (WPRO IN) - Overview | D157: Market Capitalization | E157: HISTORICAL_MARKET_CAP | F157: Last 12M | G157: 09/30/2026 | H157: 0 | I157: 1822599.3
A158: FA_dqo4tbkk.xlsx | B158: Wipro Ltd (WPRO IN) - Overview | D158: Trailing 12M EBITDA Margin | E158: EBITDA_MARGIN | F158: FY 2027 Est | G158: 03/31/2027 | H158: 1 | I158: 19.605597
A159: FA_dqo4tbkk.xlsx | B159: Wipro Ltd (WPRO IN) - Overview | D159: Trailing 12M EBITDA Margin | E159: EBITDA_MARGIN | F159: FY 2028 Est | G159: 03/31/2028 | H159: 1 | I159: 19.665856
A160: FA_dqo4tbkk.xlsx | B160: Wipro Ltd (WPRO IN) - Overview | D160: Net Income (Losses) | E160: NET_INCOME | F160: Last 12M | G160: 09/30/2026 | H160: 0 | I160: 131734
A161: FA_dqo4tbkk.xlsx | B161: Wipro Ltd (WPRO IN) - Overview | D161: Net Income (Losses) | E161: NET_INCOME | F161: FY 2027 Est | G161: 03/31/2027 | H161: 1 | I161: 133287.59
A162: FA_dqo4tbkk.xlsx | B162: Wipro Ltd (WPRO IN) - Overview | D162: Net Income (Losses) | E162: NET_INCOME | F162: FY 2028 Est | G162: 03/31/2028 | H162: 1 | I162: 136856.46
A163: FA_dqo4tbkk.xlsx | B163: Wipro Ltd (WPRO IN) - Overview | D163: Trailing 12M Earnings per Share | E163: TRAIL_12M_EPS | F163: Last 12M | G163: 09/30/2026 | H163: 0 | I163: 12.75
A164: FA_dqo4tbkk.xlsx | B164: Wipro Ltd (WPRO IN) - Overview | D164: Trailing 12M Earnings per Share | E164: TRAIL_12M_EPS | F164: FY 2027 Est | G164: 03/31/2027 | H164: 1 | I164: 13.261
A165: FA_dqo4tbkk.xlsx | B165: Wipro Ltd (WPRO IN) - Overview | D165: Trailing 12M Earnings per Share | E165: TRAIL_12M_EPS | F165: FY 2028 Est | G165: 03/31/2028 | H165: 1 | I165: 13.733
... A189: FA_dqo4tbkk.xlsx | B189: Wipro Ltd (WPRO IN) - Overview | D189: Free Cash Flow | E189: CF_FREE_CASH_FLOW | F189: FY 2028 Est | G189: 03/31/2028 | H189: 1 | I189: 143429.12
A190: FA_ni5bklkz.xlsx | B190: Wipro Ltd (WPRO IN) - Yield Analysis | C190: T12 Cash Flows to Equity | D190: + Cash From Operations | E190: TRAIL_12M_CASH_FROM_OPER | F190: FY 2027 Est | G190: 03/31/2027 | H190: 1 | I190: 170500.93
A191: FA_ni5bklkz.xlsx | B191: Wipro Ltd (WPRO IN) - Yield Analysis | C191: T12 Cash Flows to Equity | D191: + Cash From Operations | E191: TRAIL_12M_CASH_FROM_OPER | F191: FY 2028 Est | G191: 03/31/2028 | H191: 1 | I191: 177897.16
A192: FA_ni5bklkz.xlsx | B192: Wipro Ltd (WPRO IN) - Yield Analysis | C192: T12 Cash Flows to Equity | D192: Free Cash Flow | E192: TRAIL_12M_FREE_CASH_FLOW | F192: FY 2027 Est | G192: 03/31/2027 | H192: 1 | I192: 148630.38
A193: FA_ni5bklkz.xlsx | B193: Wipro Ltd (WPRO IN) - Yield Analysis | C193: T12 Cash Flows to Equity | D193: Free Cash Flow | E193: TRAIL_12M_FREE_CASH_FLOW | F193: FY 2028 Est | G193: 03/31/2028 | H193: 1 | I193: 157685.27
A194: FA_qqqxrrts.xlsx | B194: Wipro Ltd (WPRO IN) - BBG Adj Highlights | D194: Market Capitalization | E194: HISTORICAL_MARKET_CAP | F194: Current/LTM | G194: 09/30/2026 | H194: 0 | I194: 1824085.1
A195: FA_qqqxrrts.xlsx | B195: Wipro Ltd (WPRO IN) - BBG Adj Highlights | D195: - Cash & Equivalents | E195: CASH_AND_MARKETABLE_SECURITIES | F195: Current/LTM | G195: 09/30/2026 | H195: 0 | I195: 436543
A196: FA_qqqxrrts.xlsx | B196: Wipro Ltd (WPRO IN) - BBG Adj Highlights | D196: + Preferred & Other | E196: PFD_EQTY_MINORTY_INTEREST | F196: Current/LTM | G196: 09/30/2026 | H196: 0 | I196: 1721
A197: FA_qqqxrrts.xlsx | B197: Wipro Ltd (WPRO IN) - BBG Adj Highlights | D197: + Total Debt | E197: SHORT_AND_LONG_TERM_DEBT | F197: Current/LTM | G197: 09/30/2026 | H197: 0 | I197: 221065
A198: FA_qqqxrrts.xlsx | B198: Wipro Ltd (WPRO IN) - BBG Adj Highlights | D198: Enterprise Value | E198: ENTERPRISE_VALUE | F198: Current/LTM | G198: 09/30/2026 | H198: 0 | I198: 1610328.1
A199: FA_qqqxrrts.xlsx | B199: Wipro Ltd (WPRO IN) - BBG Adj Highlights | D199: Revenue, Adj | E199: SALES_REV_TURN | F199: Current/LTM | G199: 09/30/2026 | H199: 0 | I199: 970234
A200: FA_qqqxrrts.xlsx | B200: Wipro Ltd (WPRO IN) - BBG Adj Highlights | D200: Revenue, Adj | E200: SALES_REV_TURN | F200: FY 2027 Est | G200: 03/31/2027 | H200: 1 | I200: 989878.6
A201: FA_qqqxrrts.xlsx | B201: Wipro Ltd (WPRO IN) - BBG Adj Highlights | D201: Revenue, Adj | E201: SALES_REV_TURN | F201: FY 2028 Est | G201: 03/31/2028 | H201: 1 | I201: 1017536.7
A202: FA_qqqxrrts.xlsx | B202: Wipro Ltd (WPRO IN) - BBG Adj Highlights | D202: Growth %, YoY | E202: SALES_GROWTH | F202: Current/LTM | G202: 09/30/2026 | H202: 0 | I202: 8.2187365
A203: FA_qqqxrrts.xlsx | B203: Wipro Ltd (WPRO IN) - BBG Adj Highlights | D203: Growth %, YoY | E203: SALES_GROWTH | F203: FY 2027 Est | G203: 03/31/2027 | H203: 1 | I203: 6.8706383
A204: FA_qqqxrrts.xlsx | B204: Wipro Ltd (WPRO IN) - BBG Adj Highlights | D204: Growth %, YoY | E204: SALES_GROWTH | F204: FY 2028 Est | G204: 03/31/2028 | H204: 1 | I204: 2.7940926
A205: FA_qqqxrrts.xlsx | B205: Wipro Ltd (WPRO IN) - BBG Adj Highlights | D205: Gross Profit, Adj | E205: GROSS_PROFIT | F205: Current/LTM | G205: 09/30/2026 | H205: 0 | I205: 280150
... A262: FA_vujtnrpj.xlsx | B262: Wipro Ltd (WPRO IN) - Comprehensive Income | D262: Basic EPS | E262: IS_EPS | F262: Last 12M | G262: 09/30/2026 | H262: 0 | I262: 12.75

Sheet BBG_KPIC_Request
A1: Which metrics the KPI Comparison file requests for each firm (quarterly, Q1 FY26–Q4 FY27). '—' = Bloomberg has no field for that firm on this screen (e.g. Infosys adjusted operating margin and attrition, HCLTech net additions). All cells currently empty — see DQ01.
A3: entity | B3: Capital Expenditures - Median | C3: Constant Currency Revenue Growth (%) | D3: Employee Attrition Rate (%) - Median | E3: Employee Utilization Rate (%) - Median | F3: Goodwill - Median | G3: Gross Margin (%) - Median | H3: IT Services Revenue | I3: Net Employee Additions - Median | J3: Operating Margin - Adjusted (%) - Median | K3: Personnel Expenses - Median | L3: Revenue per Employee - Median | M3: Total Employees - Median
A4: WPRO IN Equity | B4: requested | C4: requested | D4: requested | E4: requested | F4: requested | G4: requested | H4: requested | I4: requested | J4: requested | K4: requested | L4: requested | M4: requested
A5: TCS IN Equity | B5: requested | C5: requested | D5: requested | E5: requested | F5: requested | G5: requested | H5: requested | I5: requested | J5: requested | K5: requested | L5: requested | M5: requested
A6: INFO IN Equity | B6: requested | C6: requested | D6: — | E6: requested | F6: requested | G6: requested | H6: requested | I6: requested | J6: — | K6: requested | L6: requested | M6: requested
A7: HCLT IN Equity | B7: requested | C7: requested | D7: requested | E7: requested | F7: requested | G7: requested | H7: requested | I7: — | J7: requested | K7: requested | L7: requested | M7: requested
A8: LTIM IN Equity | B8: requested | C8: requested | D8: requested | E8: requested | F8: requested | G8: requested | H8: requested | I8: requested | J8: requested | K8: requested | L8: — | M8: requested
A9: TECHM IN Equity | B9: requested | C9: requested | D9: requested | E9: requested | F9: requested | G9: requested | H9: requested | I9: requested | J9: requested | K9: requested | L9: requested | M9: requested
A10: MPHL IN Equity | B10: requested | C10: requested | D10: — | E10: requested | F10: requested | G10: requested | H10: requested | I10: requested | J10: requested | K10: requested | L10: — | M10: requested
A11: 018260 KS Equity | B11: requested | C11: — | D11: — | E11: — | F11: — | G11: requested | H11: requested | I11: — | J11: requested | K11: — | L11: requested | M11: —
A12: 4307 JP Equity | B12: requested | C12: — | D12: — | E12: — | F12: — | G12: requested | H12: requested | I12: — | J12: — | K12: — | L12: — | M12: —
A13: 9613 JP Equity | B13: requested | C13: — | D13: — | E13: — | F13: requested | G13: requested | H13: requested | I13: — | J13: requested | K13: requested | L13: — | M13: —
A14: ACN US Equity | B14: requested | C14: requested | D14: requested | E14: requested | F14: requested | G14: requested | H14: requested | I14: requested | J14: requested | K14: — | L14: requested | M14: requested
... A28: TEP FP Equity | B28: requested | C28: requested | D28: — | E28: — | F28: requested | G28: requested | H28: requested | I28: — | J28: requested | K28: requested | L28: requested | M28: requested

Sheet Changelog
A1: version | B1: date | C1: author | D1: change
A2: v0.0 | B2: (pull date — fill in) | C2: Team J | D2: Raw Bloomberg exports saved (26 files) — raw/bloomberg_v0, SHA-256 in raw/MANIFEST.csv
A3: v1.0 | B3: 2026-10-23 | C3: James Mathew | D3: Bloomberg audit; Wipro quarterly panel Q1 FY20–Q2 FY27 (30 quarters) from company datasheets; peer rows; 16 margin-walk records; 4 policy events; DQ log; coverage check
A4: v1.1 | B4: 2026-10-23 | C4: James Mathew | D4: Peer panel rebuilt from company fact sheets, investor releases and SEC/NSE/BSE filings (sources S42–S64): Infosys 20, TCS 19, HCLTech 9, LTIMindtree 11, Tech Mahindra 9 quarters. MW01 bps-per-point now computable. Bloomberg no longer on the critical path.
A5: v1.2 | B5: 2026-10-23 | C5: James Mathew | D5: Wipro back-filled to Q1 FY15 (50 quarters); Infosys to Q4 FY19; LTIMindtree and Tech Mahindra extended with utilisation; Wage_Hikes, FX_USDINR and TCS_Commentary sheets; panel columns for wage-hike quarter, USD/INR and one-offs; 12 more margin walks (MW03 dated to Q2 FY21); sources S65–S107.
A6: v1.3 | B6: 2026-10-23 | C6: James Mathew | D6: TCS attrition completed for all 19 quarters from company fact sheets and call transcripts (sources S108–S120); note on TCS switching to 'voluntary LTM' attrition from Q2 FY26.
A7: v1.4 (planned) | D7: Infosys Q2 FY27 when published; Wipro Q3 FY27 (first post-policy quarter, ~Jan 2027); earlier wage-hike cycles
